{
    "_id": "BG14.20",
    "chapter": 14,
    "verse": 20,
    "speaker": {
        "hi": "श्रीभगवान्",
        "be": "শ্রীভগবান্",
        "en": "Sri Bhagavan",
        "ka": "ಶ್ರೀಭಗವಾನ್"
    },
    "slok": {
        "hi": "गुणानेतानतीत्य त्रीन्देही देहसमुद्भवान् |\nजन्ममृत्युजरादुःखैर्विमुक्तोऽमृतमश्नुते ||१४-२०||",
        "be": "গুণানেতানতীত্য ত্রীন্দেহী দেহসমুদ্ভবান্ |\nজন্মমৃত্যুজরাদুঃখৈর্বিমুক্তোঽমৃতমশ্নুতে ||১৪-২০||",
        "en": "guṇānetānatītya trīndehī dehasamudbhavān .\njanmamṛtyujarāduḥkhairvimukto.amṛtamaśnute ||14-20||",
        "ka": "ಗುಣಾನೇತಾನತೀತ್ಯ ತ್ರೀನ್ದೇಹೀ ದೇಹಸಮುದ್ಭವಾನ್ |\nಜನ್ಮಮೃತ್ಯುಜರಾದುಃಖೈರ್ವಿಮುಕ್ತೋಽಮೃತಮಶ್ನುತೇ ||೧೪-೨೦||"
    },
    "transliteration": "guṇānetānatītya trīndehī dehasamudbhavān .\njanmamṛtyujarāduḥkhairvimukto.amṛtamaśnute ||14-20||",
    "tej": {
        "author": "Swami Tejomayananda",
        "commentary": {
            "hi": "।।14.20।। यह देही पुरुष शरीर की उत्पत्ति के कारणरूप तीनों गुणों से अतीत होकर जन्म, मृत्यु, जरा और दु:खों से विमुक्त हुआ अमृतत्व को प्राप्त होता है।।",
            "en": "14.20 Having transcended these three Gunas which are the origin of the body, the embodied self, freed from birth, death, old age, and pain, attains immortality.",
            "be": "।।১৪.২০।। এই দেহী পুরুষ শরীরের উৎপত্তির কারণস্বরূপ তিনটি গুণকে অতিক্রম করে জন্ম, মৃত্যু, জরা ও দুঃখ থেকে মুক্ত হয়ে অমৃতত্ব লাভ করেন।।",
            "ka": "।।೧೪.೨೦।। ಈ ದೇಹಿಯು ಶರೀರದ ಉತ್ಪತ್ತಿಗೆ ಕಾರಣವಾದ ಮೂರೂ ಗುಣಗಳನ್ನು ಮೀರಿ, ಜನ್ಮ, ಮೃತ್ಯು, ಮುಪ್ಪು ಮತ್ತು ದುಃಖಗಳಿಂದ ಮುಕ್ತನಾಗಿ ಅಮೃತತ್ವವನ್ನು ಪಡೆಯುತ್ತಾನೆ।।"
        }
    },
    "siva": {
        "author": "Swami Sivananda",
        "commentary": {
            "hi": "।।14.20।। देहधारी जीव, शरीर को उत्पन्न करने वाले इन तीनों गुणों का अतिक्रमण करके, जन्म, मृत्यु, वृद्धावस्था और दुःखों से मुक्त होकर अमरता को प्राप्त होता है。\n\n14.20 गुणान् - गुणों का; एतान् - इन; अतीत्य - पार करके; त्रीन् - तीनों; देही - देहधारी जीव; देहसमुद्भवान् - जिनसे शरीर उत्पन्न होता है; जन्ममृत्युजरादुःखैः - जन्म, मृत्यु, जरा और दुःखों से; विमुक्तः - मुक्त होकर; अमृतम् - अमरता; अश्नुते - प्राप्त करता है।\n\nभाष्य: जिस प्रकार नदी समुद्र में विलीन हो जाती है, उसी प्रकार जो मनुष्य जीवित रहते हुए ही उन तीनों गुणों से परे चला गया है जो सभी शरीरों की उत्पत्ति के बीज हैं और जिनसे वे बने हैं, वह मुझमें विलीन हो जाता है। वह सदा शाश्वत के आनन्द का उपभोग करता है। वह मुक्ति या मोक्ष प्राप्त करता है। वह मेरे स्वरूप को प्राप्त होता है। जब भगवान् ने कहा कि ज्ञानी पुरुष तीनों गुणों को पार करके अमरता को प्राप्त होता है, तब अर्जुन इसके बारे में और अधिक जानने की इच्छा से प्रेरित हुए। जिस प्रकार उन्होंने अध्याय 2 के श्लोक 54 में स्थितप्रज्ञ के बारे में प्रश्न पूछा था, उसी प्रकार अब वे भगवान् श्रीकृष्ण से उस ज्ञानी के लक्षणों के बारे में पूछते हैं जिसने तीनों गुणों को पार कर लिया है। वह कैसे आचरण करता है? उसका व्यवहार क्या है? वह गुणों से परे कैसे गया है?",
            "en": "14.20 The embodied one having crossed beyond these three Gunas out of which the body is evolved, is freed from birth, death, decay and pain, and attains to immortality.\n\n14.20 गुणान् Gunas? एतान् these? अतीत्य having crossed? त्रीन् three? देही the embodied? देहसमुद्भवान् out of which the body is evolved? जन्ममृत्युजरादुःखैः from birth? death? decay and pain? विमुक्तः freed? अमृतम् immortality? अश्नुते attains to.Commentary Just as a river is absorbed in the ocean? so also he who has? while still alive? gone beyond the alities which form the seed from which all bodies have sprung and of which they are composed? is absorbed in Me. He ever enjoys the bliss of the Eternal. He attains release or Moksha. He attains to My Being.When the Lord said that the wise man crosses beyond the three alities and attains immortality? Arjuna became inspired with the desire of learning more about it. Just as he has asked a estion about the sage of steady wisdom in chapter II? verse 54? he now asks Lord Krishna about the characteristics of a sage who has crossed over the three alities. How does he act What is his conduct or behaviour How has he gone beyond the alities",
            "be": "।।১৪.২০।। দেহধারী জীব, শরীর উৎপন্নকারী এই তিনটি গুণকে অতিক্রম করে, জন্ম, মৃত্যু, জরা ও দুঃখ থেকে মুক্ত হয়ে অমৃতত্ব লাভ করেন।\n\n১৪.২০ গুণান্ - গুণসমূহ; এতান্ - এই; অতীত্য় - অতিক্রম করে; ত্রীন্ - তিনটি; দেহী - দেহধারী জীব; দেহসমুদ্ভবান্ - যা থেকে শরীর উৎপন্ন হয়; জন্মমৃত্যুজরাদুঃখৈঃ - জন্ম, মৃত্যু, জরা ও দুঃখ থেকে; বিমুক্তঃ - মুক্ত হয়ে; অমৃতম্ - অমৃতত্ব; অশুতে - লাভ করে।\n\nভাষ্য: যেমন নদী সমুদ্রে বিলীন হয়ে যায়, তেমনই যিনি জীবিত থাকতেই সেই তিনটি গুণের অতীত হয়েছেন, যা সমস্ত শরীরের উৎপত্তির বীজ এবং যা দিয়ে শরীর গঠিত, তিনি আমাতে বিলীন হন। তিনি সর্বদা শাশ্বতের আনন্দ উপভোগ করেন। তিনি মুক্তি বা মোক্ষ লাভ করেন। তিনি আমার স্বরূপ প্রাপ্ত হন। ভগবান্ যখন বললেন যে জ্ঞানী ব্যক্তি তিনটি গুণকে অতিক্রম করে অমৃতত্ব লাভ করেন, তখন অর্জুন এ বিষয়ে আরও জানার ইচ্ছায় অনুপ্রাণিত হলেন। যেভাবে তিনি দ্বিতীয় অধ্যায়ের ৫৪ নম্বর শ্লোকে স্থিতপ্রজ্ঞের বিষয়ে প্রশ্ন করেছিলেন, তেমনই এখন তিনি ভগবান্ শ্রীকৃণের কাছে সেই জ্ঞানীর লক্ষণ সম্পর্কে জিজ্ঞাসা করছেন যিনি তিনটি গুণ অতিক্রম করেছেন। তিনি কীভাবে কাজ করেন? তাঁর আচরণ বা ব্যবহার কেমন? তিনি কীভাবে গুণসমূহ অতিক্রম করেছেন?",
            "ka": "।।೧೪.೨೦।। ಶರೀರಕ್ಕೆ ಕಾರಣವಾದ ಈ ಮೂರು ಗುಣಗಳನ್ನು ಮೀರಿ ನಿಂತ ದೇಹಿಯು ಜನ್ಮ, ಮೃತ್ಯು, ಮುಪ್ಪು ಮತ್ತು ದುಃಖಗಳಿಂದ ಮುಕ್ತನಾಗಿ ಅಮೃತತ್ವವನ್ನು ಪಡೆಯುತ್ತಾನೆ.\n\n೧೪.೨೦ ಗುಣಾನ್ - ಗುಣಗಳನ್ನು; ಏತಾನ್ - ಈ; ಅತ್ಯೀತ್ಯ - ಮೀರಿ; ತ್ರೀನ್ - ಮೂರು; ದೇಹೀ - ದೇಹಧಾರಿ; ದೇಹಸಮುದ್ಭವ್ಯಾನ್ - ಶರೀರದ ಉತ್ಪತ್ತಿಗೆ ಕಾರಣವಾದ; ಜನ್ಮಮೃತ್ಯುಜರಾದುಃಖೈಃ - ಜನ್ಮ, ಮೃತ್ಯು, ಮುಪ್ಪು ಮತ್ತು ದುಃಖಗಳಿಂದ; ವಿಮುಕ್ತಃ - ಮುಕ್ತನಾಗಿ; ಅಮೃತಮ್ - ಅಮೃತತ್ವವನ್ನು; ಅಶ್ನುತೇ - ಪಡೆಯುತ್ತಾನೆ.\n\nವ್ಯಾಖ್ಯಾನ: ನದಿಯು ಸಮುದ್ರದಲ್ಲಿ ವಿಲೀನವಾಗುವಂತೆ, ಜೀವಂತವಾಗಿದ್ದಾಗಿಯೇ ಶರೀರಗಳ ಉತ್ಪತ್ತಿಗೆ ಬೀಜವಾದ ಮತ್ತು ಶರೀರಗಳನ್ನು ನಿರ್ಮಿಸಿರುವ ಗುಣಗಳನ್ನು ಮೀರಿ ನಿಂತವನು ನನ್ನಲ್ಲಿ ವಿಲೀನನಾಗುತ್ತಾನೆ. ಅವನು ಎಂದಿಗೂ ನಿತ್ಯಾನಂದವನ್ನು ಅನುಭವಿಸುತ್ತಾನೆ. ಅವನು ಮುಕ್ತಿ ಅಥವಾ ಮೋಕ್ಷವನ್ನು ಪಡೆಯುತ್ತಾನೆ. ಅವನು ನನ್ನ ಸ್ವರೂಪವನ್ನು ತಲುಪುತ್ತಾನೆ. ಜ್ಞಾನಿಯು ಮೂರು ಗುಣಗಳನ್ನು ದಾಟಿ ಅಮೃತತ್ವವನ್ನು ಪಡೆಯುತ್ತಾನೆ ಎಂದು ಭಗವಂತನು ಹೇಳಿದಾಗ, ಅರ್ಜುನನು ಇದರ ಬಗ್ಗೆ ಹೆಚ್ಚು ತಿಳಿಯಲು ಪ್ರೇರಿತನಾಗುತ್ತಾನೆ. ೨ನೇ ಅಧ್ಯಾಯದ ೫೪ನೇ ಶ್ಲೋಕದಲ್ಲಿ ಸ್ಥಿತಪ್ರಜ್ಞನ ಬಗ್ಗೆ ಪ್ರಶ್ನಿಸಿದಂತೆ, ಈಗ ಅರ್ಜುನನು ಮೂರು ಗುಣಗಳನ್ನು ದಾಟಿದ ಜ್ಞಾನಿಯ ಲಕ್ಷಣಗಳ ಬಗ್ಗೆ ಶ್ರೀಕೃಷ್ಣನನ್ನು ಕೇಳುತ್ತಾನೆ. ಅವನು ಹೇಗೆ ವರ್ತಿಸುತ್ತಾನೆ? ಅವನ ನಡವಳಿಕೆ ಹೇಗಿರುತ್ತದೆ? ಅವನು ಗುಣಗಳನ್ನು ಹೇಗೆ ಮೀರಿದ್ದಾನೆ?"
        }
    },
    "purohit": {
        "author": "Shri Purohit Swami",
        "commentary": {
            "hi": "।।14.20।। जब आत्मा उन गुणों से अतीत हो जाती है, जो भौतिक अस्तित्व के वास्तविक कारण हैं, तब वह जन्म, मृत्यु, वृद्धावस्था और दुःखों से मुक्त होकर अमरता के अमृत का पान करती है।",
            "en": "14.20 When the soul transcends the Qualities, which are the real cause of physical existence, then, freed from birth and death, from old age and misery, he quaffs the nectar of immortality.",
            "be": "।।১৪.২০।। আত্মা যখন সেই গুণসমূহকে অতিক্রম করে, যা ভৌতিক অস্তিত্বের মূল কারণ, তখন সে জন্ম, মৃত্যু, জরা ও দুঃখ থেকে মুক্ত হয়ে অমৃতত্বের সুধা পান করে।",
            "ka": "।।೧೪.೨೦।। ಆತ್ಮವು ಭೌತಿಕ ಅಸ್ತಿತ್ವಕ್ಕೆ ಮೂಲ ಕಾರಣವಾದ ಗುಣಗಳನ್ನು ಮೀರಿದಾಗ, ಜನ್ಮ, ಮೃತ್ಯು, ಮುಪ್ಪು ಮತ್ತು ದುಃಖಗಳಿಂದ ಮುಕ್ತವಾಗಿ ಅಮೃತತ್ವದ ಸುಧೆಯನ್ನು ಸವಿಯುತ್ತದೆ."
        }
    },
    "chinmay": {
        "author": "Swami Chinmayananda",
        "commentary": {
            "hi": "।।14.20।। पाठशाला में कार्यकर रहे व्यक्ति को अग्नि की उष्णता और धुंए का कष्टसहना पड़ता है? तो ग्रीष्म काल की धूप में खड़े व्यक्ति को सूर्य के ताप और चमक को सहन करना पड़ता है। यदि ये दोनों व्यक्ति अपने उन स्थानों से हटकर अन्य शीतल स्थान पर चले जायें? तो उनके कष्टों की निवृत्ति हो जायेगी। इसी प्रकार? हम अपनी उपाधियों में क्रीड़ा कर रहे तीन गुणों के साथ तादात्म्य करके सांसारिक जीवन के बन्धनों और दुखों को भोग रहे हैं। इनसे अतीत हो जाने पर इनकी क्रूरता का अन्त हो जाता है? क्योंकि परिपूर्ण सच्चिदानन्द आत्मा में इन सबका कोई अस्तित्व नहीं है।यहाँ सत्त्वादि गुणों को शरीर की उत्पत्ति का कारण बताया गया है। वेदान्त की भाषा में आत्मस्वरूप के अज्ञान को कारण शरीर कहते हैं जिसका अनुभव हमें अपनी निद्रावस्था में होता है। इन तीनों गुण से भिन्न यह अज्ञान कोई वस्तु नहीं है। इस कारण अवस्था से ये त्रिगुण? सूक्ष्म शरीर अर्थात् अन्तकरण की विभिन्न वृत्तियों और भावनाओं के रूप में व्यक्त होते हैं। विचाररूप में परिणत ये गुण शुभ या अशुभ कर्मों के रूप में व्यक्त होने के लिये स्थूल शरीर का रूप ग्रहण करते हैं।प्रत्येक व्यक्ति को अपने विचारों और भावनाओं को प्रगट करने के लिए एक उपयुक्त माध्यम की आवश्यकता होती है। उदाहरणार्थ? चित्रकार को एक पट? तूलिका और रंगों की? तो संगीतज्ञ को वाद्यों की आवश्यकता होती है। चित्रकार को वाद्य और संगीतज्ञ के हाथ में तूलिका देने से दोनों को कोई लाभ नहीं होगा। इसी प्रकार? पशु की वृत्तियों वाले जीव को पशु का देह धारण करना मनुष्य शरीर की अपेक्षा अधिक उपयुक्त होगा। यह सब कार्य इन तीन गुणों का ही है।इससे स्पष्ट हो जाता है कि त्रिगुणों से परे पहुँचा हुआ व्यक्ति सूक्ष्म और कारण शरीरों के दुखों से भी मुक्त हो जाता है।विकार और परिवर्तन जड़ पदार्थ के धर्म हैं। अत भौतिक तत्त्वों से बने हुये सभी स्थूल शरीर विकारों को प्राप्त होते हैं? जिनका क्रम है  जन्म? वृद्धि? व्याधि? जरा (क्षय) और मृत्यु। इनमें से प्रत्येक विकार दुखदायक होता है। जन्म में पीड़ा है वृद्धि व्यथित करने वाली है? वृद्धावस्था विचलित करने वाली है? व्याधि अत्यन्त क्रूर है तो मृत्यु अत्यन्त भयंकर परन्तु ये समस्त दुख देहाभिमानी अज्ञानी जीव को ही होते हैं? आत्म स्वरूप में स्थित आत्मज्ञानी को नहीं? क्योंकि वह अपने उपाधियों से परे स्वरूप को पहचान लेता है। बाढ़? अकाल? युद्ध? महामारी? अन्त्येष्टि? विवाह एवं अन्य सहस्र घटनाओं को सूर्य प्रकाशित करता है? किन्तु सूर्य में इनमें से एक भी घटना का अस्तित्व नहीं है। इसी प्रकार आत्मचैतन्य हमारी उपाधियों को तथा तत्संबंधित अनुभवों को प्रकाशित करता है? परन्तु उसका इन सबके साथ कोई सम्बन्ध नहीं होता। अत आत्मवित् पुरुष इन सभी संघर्षों से मुक्त हो जाता है।और वह अमृतत्त्व को प्राप्त होता है  आत्मज्ञान का फल केवल दुख निवृत्ति ही नहीं वरन् परमानन्द प्राप्त भी है। भगवान् के कथन में इसी तथ्य का निर्देश है। निद्रावस्था में रोगी व्यक्ति अपनी पीड़ा को भूल जाता है निराश व्यक्ति अपनी निराशाओं से मुक्त हो जाता है क्षुधा से व्याकुल पुरुष को क्षुधा का अनुभव नहीं होता और दुखी को दुख का विस्मरण हो जाता है। परन्तु? इससे यह नहीं कहा जा सकता है कि रोगोपशम हो गया? निराशा निवृत्त हो गयी? क्षुधा शांत हो गयी और दुख का शमन हो गया। निद्रा तो वर्तमान दुख के साथ होने वाली अस्थायी सन्धिमात्र है। जाग्रत अवस्था में आने पर पुन ये सब दुख भी लौटकर आ जाते हैं। परन्तु आत्मानुभूति में दुखों की आत्यन्तिक निवृत्ति और परमानन्द की प्राप्ति होती है। इसलिये यहाँ कहा गया है कि अमृतत्त्व अर्थात् मोक्ष की इस स्थिति को इसी जगत् में? इसी जीवन में और इसी देह में रहते हुये प्राप्त किया जा सकता है। इस पृथ्वी पर ईश्वरीय पुरुष बनने का अनुभव वास्तव में विरला है। ऐसे मुक्त पुरुष के लक्षण क्या हैं? जिन्हें जानकर हम उसे समझ सकें और अपने में भी उस स्थिति को पाने का प्रयत्न कर सकें  वह जगत् में किस प्रकार व्यवहार करेगा तथा जगत् के साथ उस ज्ञानी का संबंध किस प्रकार का होगा प्रश्न पूछने के लिये एक अवसर पाकर अर्जुम पूछता है",
            "en": "14.20 A person working in a kitchen has to endure the heat and smoke of the fire, while a person standing in the summer sun has to bear the heat and glare of the sun. If both of them move away from those places to a cool place, their distress will end. Similarly, by identifying with the three Gunas playing in our equipments (upadhis), we suffer the bondages and sorrows of worldly life. Transcending them puts an end to their cruelty, for in the infinite, all-pervading Sat-Chit-Ananda Atman, none of these exist.\n\nHere, the Gunas starting with Sattva are described as the origin of the body. In the language of Vedanta, ignorance of the Self is called the causal body (karana sarira), which we experience in deep sleep. This ignorance is nothing other than these three Gunas. From this causal state, these three Gunas express as the subtle body (sukshma sarira)—the various thoughts and emotions of the mind and intellect. These Gunas, transformed into thoughts, assume the gross body to express themselves in noble or ignoble actions.\n\nEvery individual needs an appropriate medium to express their thoughts and emotions. For instance, a painter needs canvas, brushes, and paints, while a musician needs instruments. Giving musical instruments to a painter or brushes to a musician benefits neither. Likewise, an embodiment with animal tendencies finds an animal body more suitable than a human body. All this is the work of the three Gunas.\n\nThus, it is clear that one who has transcended the three Gunas is also freed from the sorrows of the subtle and causal bodies. Modifications and changes are the properties of inert matter. Hence, all gross bodies made of physical elements undergo changes, the sequence being birth, growth, disease, old age (decay), and death. Each of these modifications is painful. There is pain in birth, growth is troubling, old age is disturbing, disease is cruel, and death is terrifying. But all these sorrows belong only to the ignorant embodied jiva, not to the Knower of the Self established in Atman, who recognizes their true nature beyond all equipments.\n\nThe sun illuminates floods, famines, wars, epidemics, funerals, weddings, and thousands of other events, yet none of these events exist in the sun. Similarly, the Consciousness of Atman illuminates our equipments and their related experiences, but has no connection with them. Therefore, the Knower of the Self is freed from all these struggles.\n\nAnd 'he attains Immortality'—the fruit of Self-realization is not merely the cessation of sorrow, but the attainment of Supreme Bliss. The Lord's statement indicates this truth. In deep sleep, a sick person forgets pain, a disappointed person is freed from disappointment, a hungry person feels no hunger, and a grieving person forgets grief. However, it cannot be said that the disease is cured, disappointment eliminated, hunger satisfied, or sorrow ended. Sleep is merely a temporary truce with present sorrow. Upon waking up, all these sorrows return. But in Self-realization, there is absolute cessation of sorrow and attainment of Supreme Bliss. Hence it is said here that this state of Immortality, i.e., Moksha, can be attained in this very world, in this very life, and while living in this very body. The experience of becoming a godlike man on this earth is rare indeed.\n\nWhat are the characteristics of such a liberated soul, knowing which we may understand him and strive to reach that state ourselves? How will he behave in the world, and what will be his relationship with the world? Finding an opportunity to ask, Arjuna inquires—",
            "be": "।।১৪.২০।। রন্ধনশালায় কর্মরত ব্যক্তিকে অগ্নির উত্তাপ ও ধোঁয়ার কষ্ট সহ্য করতে হয়, আর গ্রীষ্মের রোদে দাঁড়িয়ে থাকা ব্যক্তিকে সূর্যের তাপ ও প্রখরতা সহ্য করতে হয়। যদি এই দুই ব্যক্তি নিজ স্থান ছেড়ে অন্য কোনো শীতল স্থানে চলে যান, তবে তাঁদের কষ্টের নিবৃত্তি ঘটে। একইভাবে, আমরা আমাদের উপাধিগুলিতে ক্রীড়ারত তিনটি গুণের সাথে তাদাত্ম্য স্থাপন করে জাগতিক জীবনের বন্ধন ও দুঃখ ভোগ করছি। গুণসমূহকে অতিক্রম করলে এদের নিষ্ঠুরতার অবসান ঘটে, কারণ পরিপূর্ণ সচ্চিদানন্দ আত্মায় এদের কোনো অস্তিত্ব নেই。\n\nএখানে সত্ত্বাদি গুণকে শরীরের উৎপত্তির কারণ বলা হয়েছে। বেদান্তের ভাষায় আত্মস্বরূপের অজ্ঞানকে কারণ শরীর বলে, যা আমরা সুষুপ্তি অবস্থায় অনুভব করি। এই তিনটি গুণ থেকে ভিন্ন এই অজ্ঞান অন্য কিছু নয়। এই কারণ অবস্থা থেকে এই ত্রিগুণ সূক্ষ্ম শরীর অর্থাৎ অন্তঃকরণের বিভিন্ন বৃত্তি ও ভাবনারূপে প্রকাশিত হয়। চিন্তারূপে পরিণত এই গুণগুলি শুভ বা অশুভ কর্মে রূপায়িত হওয়ার জন্য স্থূল শরীরের রূপ গ্রহণ করে。\n\nপ্রত্যেক ব্যক্তির নিজের চিন্তা ও ভাব প্রকাশ করার জন্য এক উপযুক্ত মাধ্যমের প্রয়োজন হয়। উদাহরণস্বরূপ, চিত্রশিল্পীর ক্যানভাস, তুলি ও রঙের প্রয়োজন, আর সঙ্গীতজ্ঞের বাদ্যযন্ত্রের প্রয়োজন। চিত্রশিল্পীকে বাদ্যযন্ত্র আর সঙ্গীতজ্ঞকে তুলি দিলে উভয়েরই কোনো লাভ হবে না। একইভাবে, পশুর বৃত্তিসম্পন্ন জীবের জন্য পশু দেহ ধারণ করা মানব দেহের চেয়ে অধিক উপযুক্ত। এই সব কার্যই এই তিন গুণের。\n\nএর থেকে স্পষ্ট হয় যে, ত্রিগুণের অতীত ব্যক্তি সূক্ষ্ম ও কারণ শরীরের দুঃখ থেকেও মুক্ত হয়ে যান। বিকার ও পরিবর্তন জড় পদার্থের ধর্ম। তাই ভৌত উপাদানে গঠিত সকল স্থূল শরীর বিকারপ্রাপ্ত হয়, যার ক্রম হলো— জন্ম, বৃদ্ধি, ব্যাধি, জরা (ক্ষয়) ও মৃত্যু। এর প্রতিটি বিকারই দুঃখদায়ক। জন্মে পীড়া, বৃদ্ধি কষ্টদায়ক, বার্ধক্য উদ্বেগজনক, ব্যাধি অত্যন্ত নিষ্ঠুর এবং মৃত্যু অত্যন্ত ভয়ানক। কিন্তু এই সমস্ত দুঃখ দেহ অভিমানী অজ্ঞানী জীবেরই হয়, আত্মস্বরূপে অবস্থিত আত্মজ্ঞানীর নয়, কারণ তিনি নিজের উপাধির অতীত স্বরূপকে চিনে নেন। বন্যা, দুর্ভিক্ষ, যুদ্ধ, মহামারী, অন্ত্যেষ্টি, বিবাহ এবং অন্যান্য সহস্র ঘটনাকে সূর্য আলোকিত করে, কিন্তু সূর্যের মধ্যে এর একটি ঘটনারও অস্তিত্ব নেই। একইভাবে আত্মচৈতন্য আমাদের উপাধি ও তৎসংক্রান্ত অভিজ্ঞতাকে আলোকিত করে, কিন্তু এদের সাথে আত্মার কোনো সম্বন্ধ নেই। অতএব আত্মজ্ঞানী পুরুষ এই সমস্ত সংগ্রাম থেকে মুক্ত হয়ে যান。\n\nএবং তিনি 'অমৃতত্ব লাভ করেন'— আত্মজ্ঞানের ফল কেবল দুঃখ নিবৃত্তিই নয়, পরমানন্দ প্রাপ্তিও বটে। ভগবানের কথায় এই সত্যেরই নির্দেশ রয়েছে। নিদ্রাবস্থায় রোগী নিজের যন্ত্রণা ভুলে যায়, হতাশ ব্যক্তি হতাশা থেকে মুক্ত হয়, ক্ষুধার্থ ব্যক্তি ক্ষুধা অনুভব করে না এবং দুঃখী দুঃখ বিস্মৃত হয়। কিন্তু এতে বলা যায় না যে রোগ সেরে গেছে, হতাশা দূর হয়েছে, ক্ষুধা শান্ত হয়েছে বা দুঃখ দূর হয়েছে। নিদ্রা হলো বর্তমান দুঃখের সাথে এক সাময়িক সন্ধিমাত্র। জাগ্রত হলে পুনরায় সেই সব দুঃখ ফিরে আসে। কিন্তু আত্মানুভূতিতে দুঃখের আত্যন্তিক নিবৃত্তি এবং পরমানন্দ প্রাপ্তি ঘটে। তাই এখানে বলা হয়েছে যে অমৃতত্ব অর্থাৎ মোক্ষের এই স্থিতি এই জগতেই, এই জীবনেই এবং এই দেহে থাকতেই লাভ করা সম্ভব। এই পৃথিবীতে ঈশ্বরতুল্য পুরুষ হওয়ার অভিজ্ঞতা বাস্তবিকই বিরল。\n\nএমন মুক্ত পুরুষের লক্ষণ কী, যা জেনে আমরা তাঁকে বুঝতে পারি এবং নিজেদের মধ্যেও সেই স্থিতি পাওয়ার চেষ্টা করতে পারি? তিনি জগতে কীভাবে আচরণ করবেন এবং জগতের সাথে সেই জ্ঞানীর সম্বন্ধ কেমন হবে? প্রশ্ন করার সুযোগ পেয়ে অর্জুন জিজ্ঞাসা করছেন—",
            "ka": "।।೧೪.೨೦।। ಅಡುಗೆಮನೆಯಲ್ಲಿ ಕೆಲಸ ಮಾಡುವ ವ್ಯಕ್ತಿಯು ಬೆಂಕಿಯ ಶಾಖ ಮತ್ತು ಹೊಗೆಯನ್ನು ಸಹಿಸಬೇಕಾಗುತ್ತದೆ, ಮತ್ತು ಬೇಸಿಗೆಯ ಬಿಸಿಲಿನಲ್ಲಿ ನಿಂತಿರುವ ವ್ಯಕ್ತಿಯು ಸೂರ್ಯನ ತಾಪ ಮತ್ತು ಬೆಳಕನ್ನು ಸಹಿಸಬೇಕಾಗುತ್ತದೆ. ಇವರಿಬ್ಬರೂ ತಮ್ಮ ಸ್ಥಳಗಳಿಂದ ಬೇರೆ ತಂಪಾದ ಸ್ಥಳಕ್ಕೆ ಹೋದರೆ, ಅವರ ಕಷ್ಟಗಳು ನಿವಾರಣೆಯಾಗುತ್ತವೆ. اسی ರೀತಿಯಾಗಿ, ನಾವು ನಮ್ಮ ಉಪಾಧಿಗಳಲ್ಲಿ ಆಡುತ್ತಿರುವ ಮೂರು ಗುಣಗಳೊಂದಿಗೆ ತಾದಾತ್ಮ್ಯ ಹೊಂದಿ ಸಾಂಸಾರಿಕ ಜೀವನದ ಬಂಧನ ಮತ್ತು ದುಃಖಗಳನ್ನು ಅನುಭವಿಸುತ್ತಿದ್ದೇವೆ. ಇವುಗಳನ್ನು ಮೀರಿದಾಗ ಇವುಗಳ ಕ್ರೂರತೆಯು ಕೊನೆಗೊಳ್ಳುತ್ತದೆ, ಏಕೆಂದರೆ ಪರಿಪೂರ್ಣ ಸಚ್ಚಿದಾನಂದ ಆತ್ಮನಲ್ಲಿ ಇವು ಯಾವುದರ ಅಸ್ತಿತ್ವವೂ ಇಲ್ಲ.\n\nಇಲ್ಲಿ ಸತ್ತ್ವಾದಿ ಗುಣಗಳನ್ನು ಶರೀರದ ಉತ್ಪತ್ತಿಗೆ ಕಾರಣವೆಂದು ಹೇಳಲಾಗಿದೆ. ವೇದಾಂತದ ಭಾಷೆಯಲ್ಲಿ ಆತ್ಮಸ್ವರೂಪದ ಅಜ್ಞಾನವನ್ನು ಕಾರಣ ಶರೀರ ಎನ್ನಲಾಗುತ್ತದೆ, ಇದನ್ನು ನಾವು ಸುಷುಪ್ತ್ಯವಸ್ಥೆಯಲ್ಲಿ ಅನುಭವಿಸುತ್ತೇವೆ. ಈ ಮೂರು ಗುಣಗಳಿಂದ ಭಿನ್ನವಾದ ಅಜ್ಞಾನವು ಮತ್ತೇನೂ ಅಲ್ಲ. ಈ ಕಾರಣ ಅವಸ್ಥೆಯಿಂದ ಈ ತ್ರಿಗುಣಗಳು ಸೂಕ್ಷ್ಮ ಶರೀರ ಅಂದರೆ ಅಂತಃಕರಣದ ವಿವಿಧ ವೃತ್ತಿಗಳು ಮತ್ತು ಭಾವನೆಗಳ ರೂಪದಲ್ಲಿ ವ್ಯಕ್ತವಾಗುತ್ತವೆ. ವಿಚಾರ ರೂಪಕ್ಕೆ ತಿರುಗಿದ ಈ ಗುಣಗಳು ಶುಭ ಅಥವಾ ಅಶುಭ ಕರ್ಮಗಳಾಗಿ ವ್ಯಕ್ತವಾಗಲು ಸ್ಥೂಲ ಶರೀರದ ರೂಪವನ್ನು ಪಡೆಯುತ್ತವೆ.\n\nಪ್ರತಿಯೊಬ್ಬ ವ್ಯಕ್ತಿಗೂ ತನ್ನ ಆಲೋಚನೆ ಮತ್ತು ಭಾವನೆಗಳನ್ನು ವ್ಯಕ್ತಪಡಿಸಲು ಸೂಕ್ತ ಮಾಧ್ಯಮದ ಅಗತ್ಯವಿರುತ್ತದೆ. ಉದಾಹರಣೆಗೆ, ಚಿತ್ರಕಾರನಿಗೆ ಕ್ಯಾನ್ವಾಸ್, ಕುಂಚ ಮತ್ತು ಬಣ್ಣಗಳು ಬೇಕು, ಸಂಗೀತಗಾರನಿಗೆ ವಾದ್ಯಗಳು ಬೇಕು. ಚಿತ್ರಕಾರನಿಗೆ ವಾದ್ಯಗಳನ್ನು ಮತ್ತು ಸಂಗೀತಗಾರನಿಗೆ ಕುಂಚವನ್ನು ನೀಡಿದರೆ ಇಬ್ಬರಿಗೂ ಪ್ರಯೋಜನವಿಲ್ಲ. ಹಾಗೆಯೇ, ಪಶು ವೃತ್ತಿಗಳಿರುವ ಜೀವಿಗೆ ಮಾನವ ಶರೀರಕ್ಕಿಂತ ಪಶು ದೇಹವನ್ನು ಧರಿಸುವುದು ಹೆಚ್ಚು ಸೂಕ್ತವಾಗಿರುತ್ತದೆ. ಇವೆಲ್ಲವೂ ಈ ಮೂರು ಗುಣಗಳ ಕಾರ್ಯಾಚರಣೆಯಾಗಿದೆ.\n\nಇದರಿಂದ ಸ್ಪಷ್ಟವಾಗುವುದೇನೆಂದರೆ ತ್ರಿಗುಣಗಳಿಂದ ಮೀರಿದ ವ್ಯಕ್ತಿಯು ಸೂಕ್ಷ್ಮ ಮತ್ತು ಕಾರಣ ಶರೀರಗಳ ದುಃಖಗಳಿಂದಲೂ ಮುಕ್ತನಾಗುತ್ತಾನೆ. ವಿಕಾರ ಮತ್ತು ಬದಲಾವಣೆಗಳು ಜಡ ವಸ್ತುವಿನ ಧರ್ಮಗಳಾಗಿವೆ. ಆದ್ದರಿಂದ ಭೌತಿಕ ತತ್ತ್ವಗಳಿಂದ ಮಾಡಲ್ಪಟ್ಟ ಎಲ್ಲಾ ಸ್ಥೂಲ ಶರೀರಗಳು ವಿಕಾರಗಳನ್ನು ಹೊಂದುತ್ತವೆ, ಅವುಗಳ ಕ್ರಮವೆಂದರೆ - ಜನ್ಮ, ವೃದ್ಧಿ, ವ್ಯಾಧಿ, ಜರಾ (ಕ್ಷಯ) ಮತ್ತು ಮೃತ್ಯು. ಇವುಗಳಲ್ಲಿ ಪ್ರತಿಯೊಂದು ವಿಕಾರವೂ ದುಃಖದಾಯಕವಾಗಿದೆ. ಜನ್ಮದಲ್ಲಿ ನೋವಿದೆ, ವೃದ್ಧಿಯು ಕ್ಲೇಶಕರ, ಮುಪ್ಪು ವಿಚಲಿತಗೊಳಿಸುತ್ತದೆ, ವ್ಯಾಧಿಯು ಅತ್ಯಂತ ಕ್ರೂರ ಮತ್ತು ಮೃತ್ಯು ಅತ್ಯಂತ ಭಯಾನಕ. ಆದರೆ ಈ ಎಲ್ಲಾ ದುಃಖಗಳು ದೇಹಾಭಿಮಾನಿಯಾದ ಅಜ್ಞಾನಿ ಜೀವಿಗೆ ಮಾತ್ರ ಉಂಟಾಗುತ್ತವೆ, ಆತ್ಮಸ್ವರೂಪದಲ್ಲಿ ನೆಲೆಸಿದ ಆತ್ಮಜ್ಞಾನಿಗಲ್ಲ; ಏಕೆಂದರೆ ಅವನು ತನ್ನ ಉಪಾಧಿಗಳನ್ನು ಮೀರಿದ ಸ್ವರೂಪವನ್ನು ಗುರುತಿಸುತ್ತಾನೆ. ಪ್ರವಾಹ, ಕ್ಷಾಮ, ಯುದ್ಧ, ಸಾಂಕ್ರಾಮಿಕ ರೋಗ, ಅಂತ್ಯಕ್ರಿಯೆ, ಮದುವೆ ಮುಂತಾದ ಸಹಸ್ರಾರು ಘಟನೆಗಳನ್ನು ಸೂರ್ಯನು ಪ್ರಕಾಶಿಸುತ್ತಾನೆ, ಆದರೆ ಸೂರ್ಯನಲ್ಲಿ ಈ ಯಾವುದೇ ಘಟನೆಯ ಅಸ್ತಿತ್ವವಿಲ್ಲ. ಅಂತೆಯೇ ಆತ್ಮಚೈತನ್ಯವು ನಮ್ಮ ಉಪಾಧಿಗಳನ್ನು ಮತ್ತು ತತ್ಸಂಬಂಧಿ ಅನುಭವಗಳನ್ನು ಪ್ರಕಾಶಿಸುತ್ತದೆ, ಆದರೆ ಅದಕ್ಕೆ ಇವು ಯಾವುದರೊಂದಿಗೂ ಸಂಬಂಧವಿಲ್ಲ. ಆದ್ದರಿಂದ ಆತ್ಮಜ್ಞಾನಿಯು ಈ ಎಲ್ಲಾ ಸಂಘರ್ಷಗಳಿಂದ ಮುಕ್ತನಾಗುತ್ತಾನೆ.\n\nಮತ್ತು ಅವನು 'ಅಮೃತತ್ವವನ್ನು ಪಡೆಯುತ್ತಾನೆ' - ಆತ್ಮಜ್ಞಾನದ ಫಲವು ಕೇವಲ ದುಃಖ ನಿವೃತ್ತಿಯಷ್ಟೇ ಅಲ್ಲ, ಪರಮಾನಂದ ಪ್ರಾಪ್ತಿಯೂ ಹೌದು. ಭಗವಂತನ ಹೇಳಿಕೆಯು ಈ ಸತ್ಯವನ್ನು ಸೂಚಿಸುತ್ತದೆ. ಸುಷುಪ್ತಿಯಲ್ಲಿ ರೋಗಿಯು ತನ್ನ ನೋವನ್ನು ಮರೆಯುತ್ತಾನೆ, ನಿರಾಶೆಗೊಂಡವನು ನಿರಾಶೆಯಿಂದ ಮುಕ್ತನಾಗುತ್ತಾನೆ, ಹಸಿದವನಿಗೆ ಹಸಿವಿನ ಅನುಭವವಾಗುವುದಿಲ್ಲ ಮತ್ತು ದುಃಖಿತನು ದುಃಖವನ್ನು ಮರೆಯುತ್ತಾನೆ. ಆದರೆ, ಇದರಿಂದ ರೋಗ ವಾಸಿಯಾಯಿತು, ನಿರಾಶೆ ನಿವಾರಣೆಯಾಯಿತು, ಹಸಿವು ಇಂಗಿತು ಅಥವಾ ದುಃಖ ಶಮನವಾಯಿತು ಎಂದು ಹೇಳಲಾಗುವುದಿಲ್ಲ. ನಿದ್ರೆಯು ಪ್ರಸ್ತುತ ದುಃಖದೊಂದಿಗೆ ತಾತ್ಕಾಲಿಕ ಒಪ್ಪಂದವಷ್ಟೇ. ಜಾಗ್ರದವಸ್ಥೆಗೆ ಬಂದಾಗ ಮತ್ತೆ ಈ ಎಲ್ಲಾ ದುಃಖಗಳು ಹಿಂತಿರುಗುತ್ತವೆ. ಆದರೆ ಆತ್ಮಾನುಭೂತಿಯಲ್ಲಿ ದುಃಖಗಳ ಅತ್ಯಂತಿಕ ನಿವೃತ್ತಿ ಮತ್ತು ಪರಮಾನಂದದ ಪ್ರಾಪ್ತಿಯಾಗುತ್ತದೆ. ಆದ್ದರಿಂದಲೇ ಇಲ್ಲಿ ಹೇಳಲಾಗಿದೆ - ಅಮೃತತ್ವ ಅಂದರೆ ಮೋಕ್ಷದ ಈ ಸ್ಥಿತಿಯನ್ನು ಈ ಜಗತ್ತಿನಲ್ಲಿ, ಈ ಜೀವನದಲ್ಲಿ ಮತ್ತು ಈ ದೇಹದಲ್ಲಿಯೇ ಜೀವಿಸಿರುವಾಗ ಪಡೆಯಬಹುದು. ಈ ಭೂಮಿಯಲ್ಲಿ ದಿವ್ಯ ಪುರುಷನಾಗುವ ಅನುಭವವು ನಿಜಕ್ಕೂ ಅಪರೂಪ.\n\nಅಂತಹ ಮುಕ್ತ ಪುರುಷನ ಲಕ್ಷಣಗಳೇನು, ಯಾವುದನ್ನು ತಿಳಿದು ನಾವು ಅವನನ್ನು ಅರ್ಥಮಾಡಿಕೊಳ್ಳಬಹುದು ಮತ್ತು ನಮ್ಮಲ್ಲಿಯೂ ಆ ಸ್ಥಿತಿಯನ್ನು ಪಡೆಯಲು ಪ್ರಯತ್ನಿಸಬಹುದು? ಅವನು ಜಗತ್ತಿನಲ್ಲಿ ಹೇಗೆ ವ್ಯವಹರಿಸುತ್ತಾನೆ ಮತ್ತು ಜಗತ್ತಿನೊಂದಿಗೆ ಆ ಜ್ಞಾನಿಯ ಸಂಬಂಧ ಹೇಗಿರುತ್ತದೆ? ಪ್ರಶ್ನೆ ಕೇಳಲು ಒಂದು ಅವಕಾಶವನ್ನು ಪಡೆದು ಅರ್ಜುನನು ಕೇಳುತ್ತಿದ್ದಾನೆ -"
        }
    },
    "san": {
        "author": "Dr.S.Sankaranarayan",
        "commentary": {
            "hi": "।।14.20।। इन तीनों गुणों (गुण-सूत्रों) का अतिक्रमण करके, जिनसे शरीर (आदि) उत्पन्न हुआ है, देही (आत्मा) जन्म, मृत्यु, वृद्धावस्था और दुःख से विमुक्त होकर अमरता को प्राप्त होता है।",
            "en": "14.20. Transcending these three Strands, of which the body  [etc.] is born, the Embodied (the Soul), being freed from birth, death, old age and sorrow, attains immortality.",
            "be": "।।১৪.২০।। এই তিনটি গুণকে অতিক্রম করে, যা থেকে শরীর (ইত্যাদি) উৎপন্ন হয়েছে, দেহী (আত্মা) জন্ম, মৃত্যু, জরা ও দুঃখ থেকে মুক্ত হয়ে অমৃতত্ব লাভ করেন।",
            "ka": "।।೧೪.೨೦।। ಶರೀರವು (ಇತ್ಯಾದಿ) ಯಾವುದರಿಂದ ಹುಟ್ಟಿದೆಯೋ ಅಂತಹ ಈ ಮೂರು ಗುಣಗಳನ್ನು ಮೀರಿ, ದೇಹಿಯು (ಆತ್ಮನು) ಜನ್ಮ, ಮೃತ್ಯು, ಮುಪ್ಪು ಮತ್ತು ದುಃಖಗಳಿಂದ ಮುಕ್ತನಾಗಿ ಅಮೃತತ್ವವನ್ನು ಪಡೆಯುತ್ತಾನೆ."
        }
    },
    "adi": {
        "author": "Swami Adidevananda",
        "commentary": {
            "hi": "।।14.20।। देहधारी आत्मा, शरीर में उत्पन्न होने वाले इन तीनों गुणों को पार करके और जन्म, मृत्यु, वृद्धावस्था तथा दुःख से मुक्त होकर अमरता को प्राप्त होता है।",
            "en": "14.20 The embodied self, crossing beyond these three Gunas which arise in the body, and freed from birth, death, age and pain, attains immortality.",
            "be": "।।১৪.২০।। দেহধারী আত্মা, শরীরে উৎপন্ন এই তিনটি গুণ অতিক্রম করে এবং জন্ম, মৃত্যু, জরা ও দুঃখ থেকে মুক্ত হয়ে অমৃতত্ব লাভ করেন।",
            "ka": "।।೧೪.೨೦।। ಶರೀರದಲ್ಲಿ ಉತ್ಪನ್ನವಾಗುವ ಈ ಮೂರು ಗುಣಗಳನ್ನು ಮೀರಿ, ಜನ್ಮ, ಮೃತ್ಯು, ಮುಪ್ಪು ಮತ್ತು ದುಃಖಗಳಿಂದ ಮುಕ್ತನಾದ ದೇಹಧಾರಿ ಆತ್ಮನು ಅಮೃತತ್ವವನ್ನು ಪಡೆಯುತ್ತಾನೆ."
        }
    },
    "gambir": {
        "author": "Swami Gambirananda",
        "commentary": {
            "hi": "।।14.20।। शरीर के कारण रूप इन तीनों गुणों का अतिक्रमण करके, देहधारी पुरुष जन्म, मृत्यु, वृद्धावस्था और दुःखों से मुक्त होकर अमरता का अनुभव करता है।",
            "en": "14.20 Having transcended these three alities which are the origin of the body, the embodied one, becoming free from birth, death, old age and sorrows, experiences Immortality.",
            "be": "।।১৪.২০।। শরীরের কারণস্বরূপ এই তিনটি গুণকে অতিক্রম করে, দেহী পুরুষ জন্ম, মৃত্যু, জরা ও দুঃখ থেকে মুক্ত হয়ে অমৃতত্ব অনুভব করেন।",
            "ka": "।।೧೪.೨೦।। ಶರೀರದ ಮೂಲ ಕಾರಣವಾದ ಈ ಮೂರು ಗುಣಗಳನ್ನು ಮೀರಿ, ದೇಹಿಯು ಜನ್ಮ, ಮೃತ್ಯು, ಮುಪ್ಪು ಮತ್ತು ದುಃಖಗಳಿಂದ ಮುಕ್ತನಾಗಿ ಅಮೃತತ್ವವನ್ನು ಅನುಭವಿಸುತ್ತಾನೆ."
        }
    },
    "madhav": {
        "author": "Sri Madhavacharya",
        "commentary": {
            "hi": "।।14.19 -- 14.20।। 'गुणों से भिन्न किसी अन्य परिणामी कर्ता को नहीं देखता' - ऐसा अर्थ है। अन्यथा (यदि परमेश्वर को कर्ता न माना जाए) तो 'यदा पश्यः पश्यते रुक्मवर्णं कर्तारमीशं पुरुषं ब्रह्मयोनिम्' (मुण्डकोपनिषद् 3.1.3) इस श्रुति का विरोध होगा। मोक्षधर्म में भी कहा गया है: 'मैं कर्ता नहीं हूँ, तुम कर्ता नहीं हो, सर्वदा प्रभु ही कर्ता हैं।'",
            "en": "14.19 -- 14.20 'He does not perceive any other modifying agent besides the Gunas.' Otherwise, if the Supreme Lord were not recognized as the ultimate Agent, it would contradict the Shruti text: 'When the seer sees the Golden-colored Creator, the Lord, the Person, the Source of Brahma' (Mundaka Upanishad 3.1.3). Also in the Mokshadharma it is stated: 'Neither am I the doer, nor are you the doer; the Lord alone is eternally the Doer.'",
            "be": "।।১৪.১৯ -- ১৪.২০।। 'গুণসমূহ ছাড়া অন্য কোনো পরিণামী কর্তাকে দেখে না' — এটাই অর্থ। অন্যথায় (ঈশ্বরকে কর্তা না মানলে) 'যদা পশ্যঃ পশ্যতে রুক্মবর্ণং কর্তারমীশং পুরুষং ব্রহ্মযোনিম্' (মুণ্ডক উপনিষদ্ ৩.১.৩) এই শ্রুতির বিরোধ ঘটবে। মোক্ষধর্মেও বলা হয়েছে: 'আমি কর্তা নই, তুমি কর্তা নও, সর্বদা প্রভু-ই কর্তা।'",
            "ka": "।।೧೪.೧೯ -- ೧೪.೨೦।। 'ಗುಣಗಳಿಗಿಂತ ಭಿನ್ನವಾದ ಇನ್ನೊಬ್ಬ ಪರಿಣಾಮಿ ಕರ್ತನನ್ನು ಕಾಣುವುದಿಲ್ಲ' ಎಂದು ಅರ್ಥ. ಇಲ್ಲದಿದ್ದರೆ 'ಯದಾ ಪಶ್ಯಃ ಪಶ್ಯತೇ ರೇಕ್ಮವರ್ಣಂ ಕರ್ತಾರಮೀಶಂ ಪುರುಷಂ ಬ್ರಹ್ಮಯೋನಿಮ್' (ಮುಂಡಕೋಪನಿಷತ್ ೩.೧.೩) ಎಂಬ ಶೃತಿವಾಕ್ಯಕ್ಕೆ ವಿರೋಧವುಂಟಾಗುತ್ತದೆ. ಮೋಕ್ಷಧರ್ಮದಲ್ಲೂ ಹೇಳಲಾಗಿದೆ: 'ನಾನು ಕರ್ತನಲ್ಲ, ನೀನು ಕರ್ತನಲ್ಲ, ನಿತ್ಯವೂ ಪ್ರಭುವೇ ಕರ್ತನು.'",
            "sa": "।।14.19 -- 14.20।।परिणामिकर्त्तारं गुणेभ्योऽन्यं न पश्यति। अन्यथा यदा पश्यः पश्यते रुक्मवर्णं कर्तारमीशं पुरुषं ब्रह्मयोनिम् [मुण्ड.3।1।3] इति श्रुतिविरोधः।नाहं कर्त्ता न कर्त्ता त्वं कर्त्ता यस्तु सदा प्रभुः इति मोक्षधर्मे।"
        }
    },
    "anand": {
        "author": "Sri Anandgiri",
        "commentary": {
            "hi": "।।14.20।। अनर्थ समूह स्वरूप (संसार) का निवारण करके विद्वान् ब्रह्मत्व को प्राप्त होता है—इस बात को प्रश्न के माध्यम से स्पष्ट करते हैं: 'कथम्' इत्यादि से। 'यथोक्तान्' पद की ही व्याख्या करते हैं: 'माया' इत्यादि से। माया ही उपाधि है, उससे बने हुए और तद्रूप सत्त्व आदि अनर्थ स्वरूप हैं—यह अर्थ है। 'इनसे उत्पन्न होते हैं' इस व्युत्पत्ति से 'देहोत्पत्ति' इत्यादि व्याख्या करते हैं। जो विद्वान् अविद्यामय गुणों का जीवित रहते हुए ही अतिक्रमण करके स्थित है, उसी की विशेषता बताते हैं: 'जन्म' इत्यादि से। पूर्व में विस्तार से कहे गए तथा प्रसंगवश यहाँ संक्षेप में कहे गए सम्यग्ज्ञान के फल का उपसंहार करते हैं: 'एवम्' इत्यादि से।",
            "en": "14.20 Dispelling the multitude of evils (samsara), the wise person attains Brahmanhood—this is explained through the question starting with 'how' etc. The term 'yathoktan' (as described) is explained with 'maya' etc. Maya itself is the adjunct; the Gunas starting with Sattva derived from it and of its nature are of the nature of evil. Deriving the etymology 'arising from these', the term 'dehasamudbhavan' is explained as the seeds of the origin of the body. The wise person who, even while living, stands having transcended these Gunas composed of ignorance, is further distinguished by 'janma' (birth) etc. He concludes the fruit of right knowledge, which was stated in detail earlier and here briefly in context, with 'evam' (thus) etc.",
            "be": "।।১৪.২০।। অনর্থের সমূহেরূপ সংসার দূর করে বিদ্বান ব্রহ্মত্ব লাভ করেন — এই বিষয়টি প্রশ্নের মাধ্যমে ব্যাখ্যা করছেন: 'কথম্' ইত্যাদি দিয়ে। 'যথোক্তান্' পদটিই ব্যাখ্যা করছেন: 'মায়া' ইত্যাদি দিয়ে। মায়াই উপাধি, তা থেকে উৎপন্ন এবং তদ্রূপ সত্ত্বাদি গুণসমূহ অনর্থস্বরূপ — এটাই অর্থ। 'এরা থেকে উৎপন্ন হয়' এই ব্যুৎপত্তি ধরে 'দেহোৎপত্তি' ইত্যাদি ব্যাখ্যা করছেন। যে বিদ্বান অবিদ্যাগ্রস্ত গুণসমূহকে জীবিত থাকতেই অতিক্রম করে অবস্থান করেন, তাঁরই বৈশিষ্ট্য বলছেন: 'জন্ম' ইত্যাদি দিয়ে। পূর্বে বিস্তারিতভাবে বলা এবং প্রসঙ্গক্রমে এখানে সংক্ষেপে বলা সম্যক্ জ্ঞানের ফলের উপসংহার করছেন: 'এবম্' ইত্যাদি দিয়ে।",
            "ka": "।।೧೪.೨೦।। ಅನರ್ಥ ಸಮೂಹ ರೂಪವಾದ ಸಂಸಾರವನ್ನು ಕಳೆದುಕೊಂಡು ಜ್ಞಾನಿಯು ಬ್ರಹ್ಮತ್ವವನ್ನು ಪಡೆಯುತ್ತಾನೆ ಎಂಬುದನ್ನು ಪ್ರಶ್ನೆಯ ಮೂಲಕ ವಿವರಿಸುತ್ತಾರೆ - 'ಕಥಮ್' ಇತ್ಯಾದಿಯಿಂದ. 'ಯಥೋಕ್ತಾನ್' ಎಂಬುದನ್ನೇ ವ್ಯಾಖ್ಯಾನಿಸುತ್ತಾರೆ - 'ಮಾಯಾ' ಇತ್ಯಾದಿಯಿಂದ. ಮಾಯೆಯೇ ಉಪಾಧಿ, ಅದರಿಂದ ಹುಟ್ಟಿದ ಮತ್ತು ತದ್ರೂಪವಾದ ಸತ್ತ್ವಾದಿಗಳು ಅನರ್ಥ ಸ್ವರೂಪವಾದವು ಎಂದರ್ಥ. 'ಇವುಗಳಿಂದ ಉಂಟಾಗುತ್ತವೆ' ಎಂಬ ವ್ಯುತ್ಪತ್ತಿಯನ್ನು ತೆಗೆದುಕೊಂಡು 'ದೇಹೋತ್ಪತ್ತಿ' ಇತ್ಯಾದಿ ವ್ಯಾಖ್ಯಾನಿಸುತ್ತಾರೆ. ಯಾವ ಜ್ಞಾನಿಯು ಅಜ್ಞಾನಮಯ ಗುಣಗಳನ್ನು ಜೀವಂತವಾಗಿದ್ದಾಗಲೇ ಮೀರಿ ನಿಲ್ಲುತ್ತಾನೋ ಅವನನ್ನೇ ವಿಶೇಷಿಸುತ್ತಾನೆ - 'ಜನ್ಮ' ಇತ್ಯಾದಿಯಿಂದ. ಹಿಂದೆ ವಿಸ್ತಾರವಾಗಿ ಹೇಳಿದ ಮತ್ತು ಪ್ರಸಂಗವಶಾತ್ ಇಲ್ಲಿ ಸಂಕ್ಷಿಪ್ತವಾಗಿ ಹೇಳಿದ ಸಮ್ಯಗ್ಜ್ಞಾನದ ಫಲವನ್ನು ಮುಕ್ತಾಯಗೊಳಿಸುತ್ತಾರೆ - 'ಏವಮ್' ಇತ್ಯಾದಿಯಿಂದ.",
            "sa": "।।14.20।।अनर्थव्रातरूपमपोह्य विद्वान्ब्रह्मत्वं प्राप्नोतीत्येतत्प्रश्नद्वारा विवृणोति -- कथमित्यादिना। यथोक्तानित्येतदेव व्याचष्टे -- मायेति। मायैवोपाधिस्तद्भूतांस्तदात्मनः सत्त्वादीननर्थरूपानित्यर्थः। एभ्यः समुद्भवन्तीति समुद्भवा देहस्य समुद्भवा देहसमुद्भवास्तानिति व्युत्पत्तिं गृहीत्वा व्याचष्टे -- देहोत्पत्तीति। यो विद्वानविद्यामयान्गुणाञ्जीवन्नेवातिक्रम्य स्थितस्तमेव विशिनष्टि -- जन्मेति। पुरस्ताद्विस्तरेणोक्तस्य प्रसङ्गादत्र संक्षिप्तस्य सम्यग्ज्ञानस्य फलमुपसंहरति -- एवमिति।"
        }
    },
    "rams": {
        "author": "Swami Ramsukhdas",
        "commentary": {
            "hi": "।।14.20।।देहधारी (विवेकी मनुष्य) देहको उत्पन्न करनेवाले इन तीनों गुणोंका अतिक्रमण करके जन्म, मृत्यु और वृद्धावस्थारूप दुःखोंसे रहित हुआ अमरताका अनुभव करता है।\n\n।।14.20।। व्याख्या --   गुणानेतानतीत्य त्रीन्देही देहसमुद्भवान् --  यद्यपि विचारकुशल मनुष्यका देहके साथ सम्बन्ध नहीं होता? तथापि लोगोंकी दृष्टिमें देहवाला होनेसे उसको यहाँ देही कहा गया है।देहको उत्पन्न करनेवाले गुण ही हैं। जिस गुणके साथ मनुष्य अपना सम्बन्ध मान लेता है? उसके अनुसार उसको ऊँचनीच योनियोंमें जन्म लेना ही पड़ता है (गीता 13। 21)।अभी इसी अध्यायके पाँचवें श्लोकसे अठारहवें श्लोकतक जिनका वर्णन हुआ है? उन्हीं तीनों गुणोंके लिये यहाँ एतान् त्रीन् गुणान् पद आये हैं। विचारकुशल मनुष्य इन तीनों गुणोंका अतिक्रमण कर जाता है अर्थात् इनके साथ अपना सम्बन्ध नहीं मानता? इनके साथ माने हुए सम्बन्धका त्याग कर देता है। कारण कि उसको यह स्पष्ट विवेक हो जाता है कि सभी गुण परिवर्तनशील हैं? उत्पन्न और नष्ट होनेवाले हैं और अपना स्वरूप गुणोंसे कभी लिप्त हुआ नहीं? हो सकता भी नहीं। ध्यान देनेकी बात है कि जिस प्रकृतिसे ये गुण उत्पन्न होते हैं? उस प्रकृतिके साथ भी स्वयंका किञ्चिन्मात्र भी सम्बन्ध नहीं है? फिर गुणोंके साथ तो उसका सम्बन्ध हो ही कैसे सकता हैजन्ममृत्युजरादुःखैर्विमुक्तोऽमृतमश्नुते -- जब इन तीनों गुणोंका अतिक्रमण कर जाता है? तो फिर उसको जन्म? मृत्यु और वृद्धावस्थाका दुःख नहीं होता। वह जन्ममृत्यु आदिके दुःखोंसे छूट जाता है क्योंकि जन्म आदिके होनेमें गुणोंका सङ्ग ही कारण है। ये गुण आतेजाते रहते हैं इनमें परिवर्तन होता रहता है। गुणोंकी वृत्तियाँ कभी सात्त्विकी? कभी राजसी और कभी तामसी हो जाती हैं परन्तु स्वयंमें कभी सात्त्विकपना? राजसपना और तामसपना आता ही नहीं। स्वयं (स्वरूप) तो स्वतः असङ्ग रहता है। इस असङ्ग स्वरूपका कभी जन्म नहीं होता। जब जन्म नहीं होता? तो मृत्यु भी नहीं होती। कारण कि जिसका जन्म होता है? उसीकी मृत्यु होती है तथा उसीकी वृद्धावस्था भी होती है। गुणोंका सङ्ग रहनेसे ही जन्म? मृत्यु और वृद्धावस्थाके दुःखोंका अनुभव होता है। जो गुणोंसे सर्वथा निर्लिप्तताका अनुभव कर लेता है? उसको स्वतःसिद्ध अमरताका अनुभव हो जाता है।देहसे तादात्म्य (एकता) माननेसे ही मनुष्य अपनेको मरनेवाला समझता है। देहके सम्बन्धसे होनेवाले सम्पूर्ण दुःखोंमें सबसे बड़ा दुःख मृत्यु ही माना गया है। मनुष्य स्वरूपसे है तो अमर ही किन्तु भोग और संग्रहमें आसक्त होनेसे और प्रतिक्षण नष्ट होनेवाले शरीरको अमर रखनेकी इच्छासे ही इसको अमरताका अनुभव नहीं होता। विवेकी मनुष्य देहसे तादात्म्य नष्ट होनेपर अमरताका अनुभव करता है।पूर्वश्लोकमें मद्भावं सोऽधिगच्छति पदोंसे भगवद्भावकी प्राप्ति कही गयी एवं यहाँ अमृतमश्नुते पदोंसे अमरताका अनुभव करनेको कहा गया -- वस्तुतः दोनों एक ही बात है।गीतामें जरामरणमोक्षाय (7। 29)? जन्ममृत्युजराव्याधिदुःखदोषानुदर्शनम् (13। 8) और यहाँ जन्ममृत्युजरादुःखैर्विमुक्तः (14। 20) -- इन तीनों जगह बाल्य और युवाअवस्थाका नाम न लेकर जरा (वृद्धावस्था) का ही नाम लिया गया है? जबकि शरीरमें बाल्य? युवा और वृद्ध -- ये तीनों ही अवस्थाएँ होती हैं। इसका कारण यह है कि बाल्य और युवाअवस्थामें मनुष्य अधिक दुःखका अनुभव नहीं करता क्योंकि इन दोनों ही अवस्थाओंमें शरीरमें बल रहता है। परन्तु वृद्धावस्थामें शरीरमें बल न रहनेसे मनुष्य अधिक दुःखका अनुभव करता है। ऐसे ही जब मनुष्यके प्राण छूटते हैं? तब वह भयंकर दुःखका अनुभव करता है।,परन्तु जो तीनों गुणोंका अतिक्रमण कर जाता है? वह सदाके लिये जन्म? मृत्यु और वृद्धावस्थाके दुःखोंसे मुक्त हो जाता है।इस मनुष्यशरीरमें रहते हुए जिसको बोध हो जाता है? उसका फिर जन्म होनेका तो प्रश्न ही पैदा नहीं होता। हाँ? उसके अपने कहलानेवाले शरीरके रहते हुए वृद्धावस्था और मृत्यु तो आयेगी ही? पर उसको वृद्धावस्था और मृत्युका दुःख नहीं होगा।वर्तमानमें शरीरके साथ स्वयंकी एकता माननेसे ही पुनर्जन्म होता है और शरीरमें होनेवाले जरा? व्याधि आदिके दुःखोंको जीव अपनेमें मान लेता है। शरीर गुणोंके सङ्गसे उत्पन्न होता है। देहके उत्पादक गुणोंसे रहित होनेके कारण गुणातीत महापुरुष देहके सम्बन्धसे होनेवाले सभी दुःखोंसे मुक्त हो जाता है।अतः प्रत्येक मनुष्यको मृत्युसे पहलेपहले अपने गुणातीत स्वरूपका अनुभव कर लेना चाहिये। गुणातीत होनेसे जरा? व्याधि? मृत्यु आदि सब प्रकारके दुःखोंसे मुक्ति हो जाती है और मनुष्य अमरताका अनुभव कर लेता है। फिर उसका पुनर्जन्म होता ही नहीं। सम्बन्ध --   गुणातीत पुरुषं दुःखोंसे मुक्त होकर अमरताको प्राप्त कर लेता है -- ऐसा सुनकर अर्जुनके मनमें गुणातीत मनुष्यके लक्षण जाननेकी जिज्ञासा हुई। अतः वे आगेके श्लोकमें भगवान्से प्रश्न करते हैं।",
            "en": "14.20 The embodied self (the wise man), transcending these three Gunas that give rise to the body, becomes free from the sorrows of birth, death, and old age, and experiences immortality.\n\n14.20 Commentary:\n'Gunānetānatītya trīndehī dehasamudbhavān' — Although a wise man has no real relation with the body, yet in the eyes of people, because he appears to possess a body, he is called 'dehī' (the embodied one) here. It is the Gunas that give rise to the body. Depending on which Guna a person attaches himself to, he has to take birth in higher or lower wombs accordingly (Gita 13.21). The words 'etān trīn guṇān' refer to these very three Gunas described from verse 5 to 18 of this chapter. The wise man transcends these three Gunas, meaning he does not consider himself connected with them and renounces any assumed relation with them. The reason is that he clearly realizes that all Gunas are subject to change, being born and destroyed, whereas his true Self is never tainted by the Gunas and can never be. It is worth noting that with Prakriti from which these Gunas arise, the Self has not even the slightest connection; how then could there be any connection with the Gunas?\n\n'Janmamṛtyujarāduḥkhairvimukto'mṛtamaśnute' — When one transcends these three Gunas, he no longer suffers the distress of birth, death, and old age. He is freed from the miseries of birth and death because attachment to the Gunas is the sole cause of birth etc. These Gunas come and go, continuously changing. The modifications of Gunas may sometimes become Sattvic, Rajasic, or Tamasic, but in the Self itself, Sattva, Rajas, or Tamas never arise. The Self is naturally unattached (asanga). This unattached Self is never born; when there is no birth, there is no death either, for only that which is born dies and ages. Miseries of birth, death, and old age are experienced only due to attachment to Gunas. One who experiences complete detachment from the Gunas realizes self-evident immortality.\n\nOnly by identifying with the body does a person consider himself mortal. Among all sorrows arising from bodily relation, death is considered the greatest. Man by nature is immortal, but due to attachment to enjoyment and accumulation, and the desire to make the ever-perishing body immortal, he fails to experience immortality. The wise person, upon destroying identification with the body, experiences immortality.\n\nIn the previous verse, attainment of the Divine nature was stated by 'madbhāvaṁ so'dhigacchati', and here experiencing immortality is stated by 'amṛtamaśnute'—in truth, both mean the same thing.\n\nIn the Gita, in 'jarāmaraṇamokṣāya' (7.29), 'janmamṛtyujarāvyādhiduḥkhadoṣānudarśanam' (13.8), and here 'janmamṛtyujarāduḥkhairvimuktaḥ' (14.20)—in all three places, instead of childhood and youth, only old age (jarā) is specifically mentioned, even though a body passes through childhood, youth, and old age. The reason is that in childhood and youth man does not experience much suffering because there is strength in the body in both these stages. But in old age, lacking bodily strength, man experiences great suffering. Likewise, when life departs, man experiences intense pain.\n\nHowever, one who transcends the three Gunas becomes forever free from the distresses of birth, death, and old age. For one who attains realization while living in this human body, there is no question of rebirth. To be sure, as long as the body called his own remains, old age and death will come, but he will not experience the sorrow of old age and death.\n\nIn the present, rebirth occurs due to assuming oneness with the body, and the jiva attributes to itself the distresses of old age, disease, etc. occurring in the body. The body is produced by association with the Gunas. Being free from the body-producing Gunas, the great soul who has transcended the Gunas is freed from all sorrows arising from bodily connection.\n\nTherefore, every person should experience their Guna-transcendent nature before death. By becoming transcendent of the Gunas, one is liberated from all kinds of sorrows like old age, disease, and death, and experiences immortality. Thereafter, he is never reborn.\n\nConnection — Hearing that the person who has transcended the Gunas becomes free from sorrows and attains immortality, Arjuna becomes curious to know the characteristics of such a person. Therefore, in the next verse, he puts his question to the Lord.",
            "be": "।।১৪.২০।। দেহধারী (বিবেকী মানুষ) দেহ উৎপাদনকারী এই তিনটি গুণকে অতিক্রম করে জন্ম, মৃত্যু ও বার্ধক্যজনিত দুঃখ থেকে মুক্ত হয়ে অমরত্ব অনুভব করেন।\n\n।।১৪.২০।। ব্যাখ্যা — \"গুণানেতানতীত্য ত্রীন্দেহী দেহসমুদ্ভবান্\" — যদিও বিচারকুশল মানুষের দেহের সাথে কোনো সম্বন্ধ থাকে না, তথাপি সাধারণ মানুষের দৃষ্টিতে দেহবিশিষ্ট হওয়ার কারণে তাঁকে এখানে \"দেহী\" বলা হয়েছে। দেহকে উৎপন্নকারী হলো এই গুণসমূহ। মানুষ যে গুণের সাথে নিজের সম্বন্ধ স্বীকার করে নেয়, সেই অনুযায়ী তাঁকে উচ্চ বা নিম্ন জোনিতে জন্ম নিতে হয় (গীতা ১৩.২১)। এই অধ্যায়ের ৫ম শ্লোকে থেকে ১৮শ শ্লোক পর্যন্ত যে তিনটি গুণের বর্ণনা করা হয়েছে, সেই তিনটি গুণের জন্যই এখানে \"এতান্ ত্রীন্ গুণান্\" পদটি এসেছে। বিবেকী মানুষ এই তিনটি গুণকে অতিক্রম করেন অর্থাৎ এদের সাথে নিজের সম্বন্ধ মানেন না, আরোপিত সম্বন্ধ ত্যাগ করেন। কারণ তাঁর স্পষ্ট বিবেক জাগ্রত হয় যে সমস্ত গুণ পরিবর্তনশীল, উৎপন্ন ও বিনষ্ট হওয়া স্বভাবসম্পন্ন এবং নিজের স্বরূপ গুণের দ্বারা কখনো লিপ্ত হয়নি ও হতে পারে না। লক্ষ্য করার বিষয় হলো যে প্রকৃতি থেকে এই গুণ উৎপন্ন হয়, সেই প্রকৃতির সাথেও আত্মার কিঞ্চিন্মাত্র সম্বন্ধ নেই; তাহলে গুণের সাথে কীভাবে সম্বন্ধ হতে পারে?\n\n\"জন্মমৃত্যুজরাদুঃখৈর্বিমুক্তোঽমৃতমশ্নুতে\" — যখন এই তিনটি গুণকে অতিক্রম করা হয়, তখন জন্ম, মৃত্যু ও বার্ধক্যের দুঃখ আর থাকে না। তিনি জন্ম-মৃত্যু আদি দুঃখ থেকে মুক্ত হন, কারণ জন্ম আদির মূল কারণই হলো গুণের সঙ্গ। এই গুণগুলি আসে আর যায়, এদের পরিবর্তন ঘটে। গুণের বৃত্তি কখনো সাত্ত্বিক, কখনো রাজসিক এবং কখনো তামসিক হয়, কিন্তু স্বরূপে কখনো সাত্ত্বিকতা, রাজসিকতা বা তামসিকতা আসে না। স্বরূপ স্বতঃই অসঙ্গ থাকে। এই অসঙ্গ স্বরূপের কখনো জন্ম হয় না। যার জন্ম নেই, তার মৃত্যুও নেই, কারণ যার জন্ম হয় তারই মৃত্যু ও বার্ধক্য ঘটে। গুণের সঙ্গ থাকার কারণেই জন্ম, মৃত্যু ও বার্ধক্যের দুঃখ অনুভূত হয়। যিনি গুণ থেকে সর্বথা নির্লিপ্ততা অনুভব করেন, তিনি স্বতঃসিদ্ধ অমরত্ব অনুভব করেন।\n\nদেহের সাথে তাদাত্ম্য (একত্ব) মানার কারণেই মানুষ নিজেকে মরণশীল মনে করে। দেহাংশজাত সমস্ত দুঃখের মধ্যে সবচেয়ে বড় দুঃখ হলো মৃত্যু। মানুষ স্বরূপে অমরই, কিন্তু ভোগ ও সঞ্চয়ে আসক্ত থাকার কারণে এবং প্রতি মুহূর্তে বিনাশশীল শরীরকে অমর রাখার ইচ্ছার কারণেই সে অমরত্ব অনুভব করতে পারে না। বিবেকী মানুষ দেহের সাথে তাদাত্ম্য নষ্ট হলে অমরত্ব অনুভব করেন।\n\nপূর্ববর্তী শ্লোকে \"মদ্ভাবং সোঽধিগচ্ছতি\" পদের দ্বারা ভগবদ্ভাব প্রাপ্তির কথা বলা হয়েছিল এবং এখানে \"অমৃতমশ্নুতে\" পদের দ্বারা অমরত্ব অনুভবের কথা বলা হয়েছে — বস্তুত উভয়ই এক কথা।\n\nগীতাতে \"জরামরণমোক্ষায়\" (৭.২৯), \"জন্মমৃত্যুজরাব্যাধিদুঃখদোষানুদর্শনম্\" (১৩.৮) এবং এখানে \"জন্মমৃত্যুজরাদুঃখৈর্বিমুক্তঃ\" (১৪.২০) — এই তিনটি স্থানে বাল্য ও যুবাবস্থার নাম না নিয়ে কেবল জরা (বার্ধক্য)-র নাম নেওয়া হয়েছে, যদিও শরীরে বাল্য, যুব ও বৃদ্ধ — এই তিনটি অবস্থাই থাকে। এর কারণ হলো বাল্য ও যুবাবস্থায় মানুষ অধিক দুঃখ অনুভব করে না কারণ এই উভয় অবস্থাতেই শরীরে বল থাকে। কিন্তু বার্ধক্যে শরীরে বল না থাকায় মানুষ অধিক দুঃখ অনুভব করে। একইভাবে মানুষের প্রাণ যখন নির্গত হয়, তখন সে ভয়ংকর দুঃখ অনুভব করে।\n\nকিন্তু যিনি তিনটি গুণ অতিক্রম করেন, তিনি সর্বদার জন্য জন্ম, মৃত্যু ও বার্ধক্যের দুঃখ থেকে মুক্ত হয়ে যান। এই মানবদেহে থাকা অবস্থায় যাঁর জ্ঞান লাভ হয়, তাঁর पुनর্জন্মের প্রশ্নই ওঠে না। হ্যাঁ, তাঁর নিজের বলে খ্যাত শরীর থাকা পর্যন্ত বার্ধক্য ও মৃত্যু তো আসবেই, কিন্তু তাঁর বার্ধক্য ও মৃত্যুর দুঃখ হবে না।\n\nবর্তমান সময়ে শরীরের সাথে আত্মার একত্ব মানার কারণেই पुनর্জন্ম হয় এবং শরীরে হওয়া জরা, ব্যাধি ইত্যাদির দুঃখকে জীব নিজের মনে করে। শরীর গুণের সঙ্গ থেকে উৎপন্ন হয়। দেহের উৎপাদক গুণ থেকে রহিত হওয়ার কারণে গুণাতীত মহাপুরুষ দেহের সম্বন্ধজাত সকল দুঃখ থেকে মুক্ত হয়ে যান।\n\nঅতএব প্রত্যেক মানুষের মৃত্যুর পূর্বেই নিজের গুণাতীত স্বরূপের অনুভূতি করে নেওয়া উচিত। গুণাতীত হলে জরা, ব্যাধি, मृत्यु আদি সকল প্রকার দুঃখ থেকে মুক্তি ঘটে এবং মানুষ অমরত্ব অনুভব করে। তারপর তাঁর আর पुनর্জন্ম হয় না।\n\nসম্বন্ধ — গুণাতীত পুরুষ দুঃখ মুক্ত হয়ে অমরত্ব লাভ করেন — এ কথা শুনে অর্জুনের মনে গুণাতীত মানুষের লক্ষণ জানার জিজ্ঞাসা জাগল। তাই তিনি পরবর্তী শ্লোকে ভগবানকে প্রশ্ন করছেন।",
            "ka": "।।೧೪.೨೦।। ದೇಹಧಾರಿ (ವಿವೇಕಿ ಮನುಷ್ಯನು) ದೇಹವನ್ನು ಉಂಟುಮಾಡುವ ಈ ಮೂರೂ ಗುಣಗಳನ್ನು ಮೀರಿ, ಜನ್ಮ, ಮೃತ್ಯು ಮತ್ತು ಮುಪ್ಪಿನಿಂದ ಉಂಟಾಗುವ ದುಃಖಗಳಿಂದ ಮುಕ್ತನಾಗಿ ಅಮೃತತ್ವವನ್ನು ಅನುಭವಿಸುತ್ತಾನೆ.\n\n।।೧೪.೨೦।। ವ್ಯಾಖ್ಯಾನ - \"ಗುಣಾನೇತಾನತೀತ್ಯ ತ್ರೀನ್ದೇಹೀ ದೇಹಸಮುದ್ಭವಾನ್\" - ವಿಚಾರವಂತ ಮನುಷ್ಯನಿಗೆ ಶರೀರದೊಂದಿಗೆ ಯಾವುದೇ ಸಂಬಂಧವಿಲ್ಲದಿದ್ದರೂ, ಜನರ ದೃಷ್ಟಿಯಲ್ಲಿ ಶರೀರವನ್ನು ಹೊಂದಿರುವುದರಿಂದ ಅವನನ್ನು ಇಲ್ಲಿ \"ದೇಹಿ\" ಎಂದು ಕರೆಯಲಾಗಿದೆ. ಶರೀರವನ್ನು ಉತ್ಪತ್ತಿ ಮಾಡುವುದು ಗುಣಗಳೇ. ಮನುಷ್ಯನು ಯಾವ ಗುಣದೊಂದಿಗೆ ತನ್ನ ಸಂಬಂಧವನ್ನು ಒಪ್ಪಿಕೊಳ್ಳುತ್ತಾನೋ, ಅದಕ್ಕೆ ಅನುಗುಣವಾಗಿ ಅವನು ಉನ್ನತ ಅಥವಾ ನೀಚ ಯೋನಿಗಳಲ್ಲಿ ಜನ್ಮ ತಳೆಯಬೇಕಾಗುತ್ತದೆ (ಗೀತಾ ೧೩.೨೧). ಈ ಅಧ್ಯಾಯದ ೫ ನೇ ಶ್ಲೋಕದಿಂದ ೧೮ ನೇ ಶ್ಲೋಕದವರೆಗೆ ವಿವರಿಸಲಾದ ಅದೇ ಮೂರು ಗುಣಗಳಿಗಾಗಿ ಇಲ್ಲಿ \"ಏತಾನ್ ತ್ರೀನ್ ಗುಣಾನ್\" ಎಂಬ ಪದಗಳನ್ನು ಬಳಸಲಾಗಿದೆ. ವಿವೇಕಿ ಮನುಷ್ಯನು ಈ ಮೂರು ಗುಣಗಳನ್ನು ಮೀರುತ್ತಾನೆ, ಅಂದರೆ ಅವುಗಳೊಂದಿಗೆ ತನ್ನ ಸಂಬಂಧವನ್ನು ಒಪ್ಪುವುದಿಲ್ಲ, ಅವುಗಳೊಂದಿಗೆ ಕಲ್ಪಿಸಿಕೊಂಡ ಸಂಬಂಧವನ್ನು ತ್ಯಜಿಸುತ್ತಾನೆ. ಏಕೆಂದರೆ ಎಲ್ಲಾ ಗುಣಗಳು ಬದಲಾಗುವಂತಹವು, ಹುಟ್ಟುವುದು ಮತ್ತು ನಾಶವಾಗುವುದು ಅವುಗಳ ಸ್ವಭಾವ, ಆದರೆ ತನ್ನ ನಿಜವಾದ ಸ್ವರೂಪವು ಎಂದಿಗೂ ಗುಣಗಳಿಂದ ಲಿಪ್ತವಾಗುವುದಿಲ್ಲ ಮತ್ತು ಆಗಲು ಸಾಧ್ಯವಿಲ್ಲ ಎಂಬ ಸ್ಪಷ್ಟ ವಿವೇಕ ಅವನಿಗೆ ಉಂಟಾಗುತ್ತದೆ. ಗಮನಿಸಬೇಕಾದ ವಿಷಯವೇನೆಂದರೆ, ಯಾವ ಪ್ರಕೃತಿಯಿಂದ ಈ ಗುಣಗಳು ಹುಟ್ಟುತ್ತವೆಯೋ, ಆ ಪ್ರಕೃತಿಯೊಂದಿಗೆ ತನ್ನ ಸ್ವಂತ ಸ್ವರೂಪಕ್ಕೆ ಸ್ವಲ್ಪವೂ ಸಂಬಂಧವಿಲ್ಲ; ಹಾಗಿರುವಾಗ ಗುಣಗಳೊಂದಿಗೆ ಸಂಬಂಧ ಹೇಗೆ ಸಾಧ್ಯ?\n\n\"ಜನ್ಮಮೃತ್ಯುಜರಾದುಃಖೈರ್ವಿಮುಕ್ತೋಽಮೃತಮಶ್ನುತೇ\" - ಈ ಮೂರು ಗುಣಗಳನ್ನು ಮೀರಿದಾಗ, ಅವನಿಗೆ ಜನ್ಮ, ಮೃತ್ಯು ಮತ್ತು ಮುಪ್ಪಿನ ದುಃಖವಿರುವುದಿಲ್ಲ. ಜನ್ಮಾದಿಗಳಾಗಲು ಗುಣಗಳ ಸಹವಾಸವೇ ಕಾರಣವಾಗಿರುವುದರಿಂದ ಅವನು ಜನ್ಮಮೃತ್ಯು ಮುಂತಾದ ದುಃಖಗಳಿಂದ ಮುಕ್ತನಾಗುತ್ತಾನೆ. ಈ ಗುಣಗಳು ಬರುತ್ತವೆ ಮತ್ತು ಹೋಗುತ್ತವೆ, ಇವುಗಳಲ್ಲಿ ಬದಲಾವಣೆಗಳು ನಡೆಯುತ್ತಿರುತ್ತವೆ. ಗುಣಗಳ ವೃತ್ತಿಗಳು ಕೇವಲ ಸಾತ್ತ್ವಿಕ, ರಾಜಸಿಕ ಅಥವಾ ತಾಮಸಿಕವಾಗಬಹುದು, ಆದರೆ ಸ್ವರೂಪದಲ್ಲಿ ಎಂದಿಗೂ ಸಾತ್ತ್ವಿಕತೆ, ರಾಜಸಿಕತೆ ಅಥವಾ ತಾಮಸಿಕತೆ ಬರುವುದೇ ಇಲ್ಲ. ಸ್ವರೂಪವು ಸ್ವತಃ ಅಸಂಗವಾಗಿರುತ್ತದೆ. ಈ ಅಸಂಗ ಸ್ವರೂಪಕ್ಕೆ ಎಂದಿಗೂ ಜನ್ಮವಿಲ್ಲ. ಜನ್ಮವಿಲ್ಲದಿದ್ದಾಗ ಮೃತ್ಯುವೂ ಇಲ್ಲ, ಏಕೆಂದರೆ ಜನ್ಮತಳೆದ ವಸ್ತುವಿಗೆ ಮಾತ್ರ ಮೃತ್ಯು ಮತ್ತು ಮುಪ್ಪು ಇರುತ್ತದೆ. ಗುಣಗಳ ಸಂಗದಿಂದ ಮಾತ್ರ ಜನ್ಮ, ಮೃತ್ಯು ಮತ್ತು ಮುಪ್ಪಿನ ದುಃಖಗಳ ಅನುಭವವಾಗುತ್ತದೆ. ಗುಣಗಳಿಂದ ಸಂಪೂರ್ಣ ನಿರ್ಲಿಪ್ತತೆಯನ್ನು ಅನುಭವಿಸುವವನು ಸ್ವತಃಸಿದ್ಧ ಅಮೃತತ್ವವನ್ನು ಅನುಭವಿಸುತ್ತಾನೆ.\n\nದೇಹದೊಂದಿಗೆ ತಾದಾತ್ಮ್ಯ (ಏಕತೆ) ಹೊಂದುವುದರಿಂದಲೇ ಮನುಷ್ಯನು ತನ್ನನ್ನು ಸಾಯುವವನೆಂದು ಭಾವಿಸುತ್ತಾನೆ. ಶರೀರದ ಸಂಬಂಧದಿಂದ ಉಂಟಾಗುವ ಎಲ್ಲಾ ದುಃಖಗಳಲ್ಲಿ ಮೃತ್ಯುವೇ ಅತ್ಯಂತ ದೊಡ್ಡ ದುಃಖವೆಂದು ಪರಿಗಣಿಸಲಾಗಿದೆ. ಮನುಷ್ಯನು ಸ್ವರೂಪತಃ ಅಮರನೇ ಆಗಿದ್ದಾನೆ, ಆದರೆ ಭೋಗ ಮತ್ತು ಸಂಗ್ರಹದಲ್ಲಿ ಆಸಕ್ತನಾಗಿರುವುದರಿಂದ ಹಾಗೂ ಪ್ರತಿಯೊಂದು ಕ್ಷಣವೂ ನಾಶವಾಗುವ ಶರೀರವನ್ನು ಅಮರವಾಗಿಸುವ ಇಚ್ಛೆಯಿಂದಾಗಿ ಅವನಿಗೆ ಅಮೃತತ್ವದ ಅನುಭವವಾಗುವುದಿಲ್ಲ. ವಿವೇಕಿ ಮನುಷ್ಯನು ದೇಹದ ತಾದಾತ್ಮ್ಯ ನಾಶವಾದಾಗ ಅಮೃತತ್ವವನ್ನು ಅನುಭವಿಸುತ್ತಾನೆ.\n\nಹಿಂದಿನ ಶ್ಲೋಕದಲ್ಲಿ \"ಮದ್ಭಾವಂ ಸೋಽಧಿಗಚ್ಛತಿ\" ಪದಗಳಿಂದ ಭಗವದ್ಭಾವದ ಪ್ರಾಪ್ತಿಯನ್ನು ಹೇಳಲಾಯಿತು ಮತ್ತು ಇಲ್ಲಿ \"ಅಮೃತಮಶ್ನುತೇ\" ಪದಗಳಿಂದ ಅಮೃತತ್ವದ ಅನುಭವವನ್ನು ಹೇಳಲಾಗಿದೆ - ವಾಸ್ತವವಾಗಿ ಎರಡೂ ಒಂದೇ ವಿಷಯ.\n\nಗೀತೆಯಲ್ಲಿ \"ಜರಾಮರಣಮೋಕ್ಷಾಯ\" (೭.೨೯), \"ಜನ್ಮಮೃತ್ಯುಜರಾವ್ಯಾಧಿ ದುಃಖದೋಷಾನುದರ್ಶನಮ್\" (೧೩.೮) ಮತ್ತು ಇಲ್ಲಿ \"ಜನ್ಮಮೃತ್ಯುಜರಾದುಃಖೈರ್ವಿಮುಕ್ತಃ\" (೧೪.೨೦) - ಈ ಮೂರೂ ಸ್ಥಳಗಳಲ್ಲಿ ಬಾಲ್ಯ ಮತ್ತು ಯೌವನಗಳ ಹೆಸರನ್ನು ಹೇಳದೆ ಜರಾ (ಮುಪ್ಪು) ಹೆಸರನ್ನು ಮಾತ್ರ ಉಲ್ಲೇಖಿಸಲಾಗಿದೆ, ಶರೀರದಲ್ಲಿ ಬಾಲ್ಯ, ಯೌವನ ಮತ್ತು ವೃದ್ಧಾಪ್ಯ ಮೂರೂ ಅವಸ್ಥೆಗಳಿದ್ದರೂ ಸಹ. ಇದರ ಕಾರಣವೇನೆಂದರೆ ಬಾಲ್ಯ ಮತ್ತು ಯೌವನದಲ್ಲಿ ಮನುಷ್ಯನು ಹೆಚ್ಚಿನ ದುಃಖವನ್ನು ಅನುಭವಿಸುವುದಿಲ್ಲ, ಏಕೆಂದರೆ ಈ ಎರಡೂ ಅವಸ್ಥೆಗಳಲ್ಲಿ ಶರೀರದಲ್ಲಿ ಬಲವಿರುತ್ತದೆ. ಆದರೆ ವೃದ್ಧಾಪ್ಯದಲ್ಲಿ ಶರೀರದಲ್ಲಿ ಬಲವಿಲ್ಲದಿರುವುದರಿಂದ ಮನುಷ್ಯನು ಹೆಚ್ಚಿನ ದುಃಖವನ್ನು ಅನುಭವಿಸುತ್ತಾನೆ. ಹಾಗೆಯೇ ಮನುಷ್ಯನ ಪ್ರಾಣ ಹೊರಡುವಾಗ ಅವನು ಭಯಾನಕ ದುಃಖವನ್ನು ಅನುಭವಿಸುತ್ತಾನೆ.\n\nಆದರೆ ಮೂರು ಗುಣಗಳನ್ನು ಮೀರುವವನು ಎಂದೆಂದಿಗೂ ಜನ್ಮ, ಮೃತ್ಯು ಮತ್ತು ಮುಪ್ಪಿನ ದುಃಖಗಳಿಂದ ಮುಕ್ತನಾಗುತ್ತಾನೆ. ಈ ಮನುಷ್ಯ ಶರೀರದಲ್ಲಿ ಜೀವಿಸಿರುವಾಗಲೇ ಯಾರಿಗೆ ಜ್ಞಾನವಾಗುತ್ತದೋ, ಅವನಿಗೆ ಮತ್ತೆ ಜನ್ಮ ಪಡೆಯುವ ಪ್ರಶ್ನೆಯೇ ಏಳುವುದಿಲ್ಲ. ಹೌದು, ತನ್ನದೆಂದು ಹೇಳಲಾಗುವ ಶರೀರವಿರುವವರೆಗೆ ಮುಪ್ಪು ಮತ್ತು ಮೃತ್ಯು ಬಂದೇ ಬರುತ್ತದೆ, ಆದರೆ ಅವನಿಗೆ ಮುಪ್ಪು ಮತ್ತು ಮೃತ್ಯುವಿನ ದುಃಖವಿರುವುದಿಲ್ಲ.\n\nವರ್ತಮಾನದಲ್ಲಿ ಶರೀರದೊಂದಿಗೆ ತನ್ನ ಏಕತೆಯನ್ನು ಒಪ್ಪಿಕೊಳ್ಳುವುದರಿಂದ ಪುನರ್ಜನ್ಮವಾಗುತ್ತದೆ ಮತ್ತು ಶರೀರದಲ್ಲಿ ಉಂಟಾಗುವ ಜರಾ, ವ್ಯಾಧಿ ಮುಂತಾದ ದುಃಖಗಳನ್ನು ಜೀವಿಯು ತನ್ನದೆಂದು ಭಾವಿಸುತ್ತಾನೆ. ಶರೀರವು ಗುಣಗಳ ಸಂಗದಿಂದ ಹುಟ್ಟುತ್ತದೆ. ದೇಹವನ್ನು ಉತ್ಪತ್ತಿ ಮಾಡುವ ಗುಣಗಳಿಂದ ರಹಿತನಾಗಿರುವುದರಿಂದ, ಗುಣಾತೀತ ಮಹಾಪುರುಷನು ದೇಹದ ಸಂಬಂಧದಿಂದ ಉಂಟಾಗುವ ಎಲ್ಲಾ ದುಃಖಗಳಿಂದ ಮುಕ್ತನಾಗುತ್ತಾನೆ.\n\nಆದ್ದರಿಂದ ಪ್ರತಿಯೊಬ್ಬ ಮನುಷ್ಯನೂ ಮೃತ್ಯುವಿಗಿಂತ ಮುಂಚೆಯೇ ತನ್ನ ಗುಣಾತೀತ ಸ್ವರೂಪದ ಅನುಭವವನ್ನು ಪಡೆಯಬೇಕು. ಗುಣಾತೀತನಾಗುವುದರಿಂದ ಜರಾ, ವ್ಯಾಧಿ, ಮೃತ್ಯು ಮುಂತಾದ ಎಲ್ಲಾ ರೀತಿಯ ದುಃಖಗಳಿಂದ ಮುಕ್ತಿಯಾಗುತ್ತದೆ ಮತ್ತು ಮನುಷ್ಯನು ಅಮೃತತ್ವವನ್ನು ಅನುಭವಿಸುತ್ತಾನೆ. ತರುವಾಯ ಅವನಿಗೆ ಪುನರ್ಜನ್ಮವೇ ಇರುವುದಿಲ್ಲ.\n\nಸಂಬಂಧ - ಗುಣಾತೀತ ಪುರುಷನು ದುಃಖಗಳಿಂದ ಮುಕ್ತನಾಗಿ ಅಮೃತತ್ವವನ್ನು ಪಡೆಯುತ್ತಾನೆ - ಇದನ್ನು ಕೇಳಿ ಅರ್ಜುನನ ಮನಸ್ಸಿನಲ್ಲಿ ಗುಣಾತೀತ ಮನುಷ್ಯನ ಲಕ್ಷಣಗಳನ್ನು ತಿಳಿಯುವ ಜಿಜ್ಞಾಸೆ ಉಂಟಾಯಿತು. ಆದ್ದರಿಂದ ಅವನು ಮುಂದಿನ ಶ್ಲೋಕದಲ್ಲಿ ಭಗವಂತನನ್ನು ಪ್ರಶ್ನಿಸುತ್ತಾನೆ."
        }
    },
    "raman": {
        "author": "Sri Ramanuja",
        "commentary": {
            "hi": "।।14.20।। यह देही (आत्मा) देह की उत्पत्ति के कारणभूत, अर्थात् देहाकार में परिणत प्रकृति से उत्पन्न इन सत्त्व आदि तीनों गुणों का अतिक्रमण करके तथा उनसे भिन्न केवल ज्ञानस्वरूप आत्मा को देखता हुआ, जन्म, मृत्यु, वृद्धावस्था और दुःख से विमुक्त होकर अमृत स्वरूप आत्मा का अनुभव करता है। 'यह मेरा भाव (सधर्मता) है' — यह अर्थ है।\n\nअब गुणातीत पुरुष के स्वरूप, उसके आचरण के प्रकार तथा गुण-अतिक्रमण के उपाय को पूछते हुए अर्जुन ने कहा —",
            "en": "14.20 The embodied self - 'crossing beyond these three Gunas,' the Sattva and the rest, which 'arise in the body,' i.e., spring from Prakrti transformed into the form of the body - perceives the self as different from the Gunas and as of the form of knowledge only. Released thus from birth, death, old age and sorrow, It experiences the immortal self. This is what is meant by My likeness.\n\nArjuna now wants to know about the characteristics of one who has transcended the Gunas and the means of such transcendence:",
            "be": "।।১৪.২০।। এই দেহী (আত্মা) দেহের উৎপত্তির কারণস্বরূপ, অর্থাৎ দে আকারে পরিণত প্রকৃতি থেকে উৎপন্ন এই সত্ত্ব আদি তিনটি গুণকে অতিক্রম করে এবং এদের থেকে ভিন্ন কেবল জ্ঞানস্বরূপ আত্মাকে দর্শন করে, জন্ম, মৃত্যু, জরা ও দুঃখ থেকে মুক্ত হয়ে অমৃতস্বরূপ আত্মাকে অনুভব করেন। 'এটিই আমার ভাব (সধর্মতা)' — এটাই অর্থ।\n\nএখন গুণাতীত পুরুষের স্বরূপ, তাঁর আচরণের প্রকার এবং গুণ অতিক্রমের উপায় জিজ্ঞাসা করে অর্জুন বললেন —",
            "ka": "।।೧೪.೨೦।। ಈ ದೇಹಿಯು (ಆತ್ಮನು) ದೇಹದ ಉತ್ಪತ್ತಿಗೆ ಕಾರಣವಾದ, ಅಂದರೆ ದೇಹಾಕಾರವಾಗಿ ಪರಿಣಮಿಸಿದ ಪ್ರಕೃತಿಯಿಂದ ಹುಟ್ಟಿದ ಈ ಸತ್ತ್ವಾದಿ ಮೂರು ಗುಣಗಳನ್ನು ಮೀರಿ, ಅವುಗಳಿಗಿಂತ ಭಿನ್ನವಾದ ಕೇವಲ ಜ್ಞಾನಸ್ವರೂಪಿಯಾದ ಆತ್ಮನನ್ನು ಕಾಣುತ್ತಾ, ಜನ್ಮ, ಮೃತ್ಯು, ಮುಪ್ಪು ಮತ್ತು ದುಃಖಗಳಿಂದ ಮುಕ್ತನಾಗಿ ಅಮೃತಸ್ವರೂಪಿಯಾದ ಆತ್ಮನನ್ನು ಅನುಭವಿಸುತ್ತಾನೆ. 'ಇದೇ ನನ್ನ ಭಾವ (ಸಾಧರ್ಮ್ಯ)' ಎಂದು ಅರ್ಥ.\n\nಈಗ ಗುಣಾತೀತನ ಸ್ವರೂಪ, ಅವನ ನಡವಳಿಕೆಯ ರೀತಿ ಮತ್ತು ಗುಣಗಳನ್ನು ಮೀರುವ ಉಪಾಯವನ್ನು ಕೇಳುತ್ತಾ ಅರ್ಜುನನು ಹೇಳಿದನು -",
            "sa": "।।14.20।।अयं देही देहसमुद्भवान् देहाकारपरिणतप्रकृतिसमुद्भवान् एतान् सत्त्वादीन् त्रीन् गुणान् अतीत्य तेभ्यः च अन्यम्? ज्ञानैकाकारम् आत्मानम् पश्यन् जन्ममृत्युजरादुःखैः विमुक्तः अमृतम् आत्मानम् अनुभवति एष मद्भाव इत्यर्थः।अथ गुणातीतस्य स्वरूपसूचनाचारप्रकारं गुणात्ययहेतुं च पृच्छन् अर्जुन उवाच --"
        }
    },
    "abhinav": {
        "author": "Sri Abhinav Gupta",
        "commentary": {
            "hi": "।।14.16 -- 14.20।। 'कर्मणः' इत्यादि से लेकर 'अश्नुते' तक। यहाँ कुछ असंबद्ध श्लोक कल्पित (जोड़े गए) हैं; पुनरुक्त होने के कारण वे त्याज्य ही हैं। यह गुणातीत स्थिति तो मोक्ष के लिए ही होती है।",
            "en": "14.16-20 Karmanah etc. upto asnute.  Here, there are certain unconnected verses that have been concocted.  They are of the nature of repetition, and hence they have to be necessarily rejected.  A mode of life transcending these Strands turn to be nothing but emancipation.",
            "be": "।।১৪.১৬ -- ১৪.২০।। 'কর্মণঃ' ইত্যাদি থেকে 'অশ্নুতে' পর্যন্ত। এখানে কিছু অসসংবদ্ধ শ্লোক কল্পিত (সংযোজিত) হয়েছে; পুনরুক্ত হওয়ার কারণে সেগুলি ত্যাজ্যই। এই গুণাতীত স্থিতি তো মোক্ষের জন্যই হয়ে থাকে।",
            "ka": "।।೧೪.೧೬ -- ೧೪.೨೦।। 'ಕರ್ಮಣಃ' ಇತ್ಯಾದಿಯಿಂದ ಹಿಡಿದು 'ಅಶ್ನುತೇ' ಕೊನೆಯವರೆಗೆ. ಇಲ್ಲಿ ಕೆಲವು ಅಸಂಬದ್ಧ ಶ್ಲೋಕಗಳನ್ನು ಕಲ್ಪಿಸಲಾಗಿದೆ; ಪುನರುಕ್ತವಾಗಿರುವುದರಿಂದ ಅವು ತ್ಯಾಜ್ಯವೇ. ಈ ಗುಣಾತೀತ ಸ್ಥಿತಿಯು ಮೋಕ್ಷಕ್ಕಾಗಿಯೇ ಇರುತ್ತದೆ.",
            "sa": "।।14.16 -- 14.20।।कर्मण इत्यादि अश्नुते इत्यन्तम्।  अत्र केचिदसंबद्धाः श्लोकाः कल्पिताः? पुनरुक्तत्वात् ( पुनरुक्तार्थत्वात्) ते त्याज्या एव।  एतद्गुणातीतवृत्तिस्तु (N गुणातीतश्रुतिस्तु) मोक्षायैव कल्पते।"
        }
    },
    "sankar": {
        "author": "Sri Shankaracharya",
        "commentary": {
            "hi": "।।14.20।।कैसे प्राप्त होता है सो बतलाते हैं --, देहोत्पत्तिके बीजभूत? इन मायोपाधिक पूर्वोक्त तीनों गुणोंका उल्लंघन कर? अर्थात् जीवितावस्थामें ही इनका अतिक्रम करके? यह देहधारी विद्वान् जीता हुआ ही जन्म मृत्यु? बुढ़ापे और दुःखोंसे मुक्त होकर अमृतका अनुभव करता है। अभिप्राय यह कि इस प्रकार वह मेरे भावको प्राप्त हो जाता है।",
            "en": "14.20 Atitya, having transcended, having gone beyond-even while living; etan, these; trin, three; gunan, alities as have been described, which constitute the limiting adjunct Maya; and dehasamudbhavan, which are the origin of the body, which are the seed of the birth of the body; dehi, the embodied one, the enlightened one; vimuktah, becoming free-even in this life; janma-mrtyu-jara-duhkhaih, from birth death, old age and sorrow; asnute, experiences; [Some translate this as 'attains'.-Tr.] amrtam, Immortality. In this way he attains My nature. This is the idea.\nGetting a clue to a estion from the statement that one experiences Immortality, even in this life, by going beyond the alities-",
            "be": "।।১৪.২০।। কীভাবে প্রাপ্ত হন তা বলছেন — মায়োপাধিক পূর্বে উল্লেখিত এই তিনটি গুণকে অতিক্রম করে, যা দেহের উৎপত্তির বীজস্বরূপ, অর্থাৎ জীবিত অবস্থাতেই এদের অতিক্রম করে, এই দেহধারী বিদ্বান জীবিত থাকতেই জন্ম, মৃত্যু, জরা ও দুঃখ থেকে মুক্ত হয়ে অমৃত অনুভব করেন। অভিপ্রায় এই যে, এইভাবে তিনি আমার ভাব (স্বরূপ) প্রাপ্ত হন।\n\nজীবিত থাকতেই গুণসমূহ অতিক্রম করে অমৃত অনুভব করেন — এই কথার সূত্র ধরে অর্জুন বললেন —",
            "ka": "।।೧೪.೨೦।। ಹೇಗೆ ಪಡೆಯುತ್ತಾನೆ ಎಂಬುದನ್ನು ಹೇಳುತ್ತಾರೆ - ಮಾಯೋಪಾಧಿ ರೂಪವಾದ ಮೇಲೆ ಹೇಳಿದ ಮೂರು ಗುಣಗಳನ್ನು ಮೀರಿ, ಅಂದರೆ ಜೀವಂತವಾಗಿರುವಾಗಲೇ ಇವುಗಳನ್ನು ದಾಟಿ, ಶರೀರದ ಉತ್ಪತ್ತಿಗೆ ಬೀಜವಾದ ಈ ಗುಣಗಳಿಂದ ಮುಕ್ತನಾಗಿ, ಈ ದೇಹಧಾರಿ ಜ್ಞಾನಿಯು ಜೀವಂತವಿರುವಾಗಲೇ ಜನ್ಮ, ಮೃತ್ಯು, ಮುಪ್ಪು ಮತ್ತು ದುಃಖಗಳಿಂದ ವಿಮುಕ್ತನಾಗಿ ಅಮೃತತ್ವವನ್ನು ಅನುಭವಿಸುತ್ತಾನೆ. ಅಂದರೆ ಈ ರೀತಿಯಾಗಿ ಅವನು ನನ್ನ ಭಾವವನ್ನು (ಸ್ವರೂಪವನ್ನು) ತಲುಪುತ್ತಾನೆ ಎಂದರ್ಥ.\n\nಜೀವಂತವಾಗಿದ್ದಾಗಿಯೇ ಗುಣಗಳನ್ನು ಮೀರಿ ಅಮೃತತ್ವವನ್ನು ಅನುಭವಿಸುತ್ತಾನೆ ಎಂಬ ಹೇಳಿಕೆಯಿಂದ ಪ್ರಶ್ನೆಗೆ ಸೂಚನೆ ಪಡೆದು, ಅರ್ಜುನನು ಹೇಳಿದನು -",
            "sa": "।।14.20।। --,गुणान् एतान् यथोक्तान् अतीत्य जीवन्नेव अतिक्रम्य मायोपाधिभूतान् त्रीन् देही देहसमुद्भवान् देहोत्पत्तिबीजभूतान् जन्ममृत्युजरादुःखैः जन्म च मृत्युश्च जरा च दुःखानि च जन्ममृत्युजरादुःखानि तैः जीवन्नेव विमुक्तः सन् विद्वान् अमृतम् अश्नुते? एवं मद्भावम् अधिगच्छति इत्यर्थः।।जीवन्नेव गुणान् अतीत्य अमृतम् अश्नुते इति प्रश्नबीजं प्रतिलभ्य? अर्जुन उवाच --,अर्जुन उवाच --,"
        }
    },
    "jaya": {
        "author": "Sri Jayatritha",
        "commentary": {
            "hi": "।।14.19 -- 14.20।। 'गुणानेतानतीत्य... नान्यं गुणेभ्यः कर्तारम्' - यहाँ केवल गुणों का ही स्वतंत्र कर्तृत्व है, किसी अन्य का नहीं—इस कुव्याख्या के निराकरण के लिए कहते हैं: 'परिणामी' इत्यादि। यह क्यों? इस पर कहते हैं: 'अन्यथा' इत्यादि, अर्थात् गुणों से भिन्न (परमेश्वर) का कर्तृत्व न मानने पर। मोक्षधर्म में परमेश्वर का कर्तृत्व कहा गया है, उससे विरोध होगा—यह वाक्य का शेष भाग है।",
            "en": "14.19 -- 14.20 'No other agent besides the Gunas...' — to refute the wrong interpretation that independent agency belongs only to the Gunas and to none else, he states: 'modifying agent...' Why so? To this he says: 'otherwise...', meaning if agency is denied to the One other than the Gunas (i.e. the Supreme Lord). In the Mokshadharma, the agency of the Supreme Lord is stated, and denying it would lead to contradiction with that—this completes the sentence.",
            "be": "।।১৪.১৯ -- ১৪.২০।। 'গুণসমূহ ছাড়া অন্য কোনো কর্তা নেই...' — এখানে কেবল গুণগুলিরই স্বতন্ত্র কর্তৃত্ব রয়েছে, অন্য কারো নয় — এই অপব্যাখ্যা নিরসনের জন্য বলছেন: 'পরিণামী' ইত্যাদি। এটি কেন? এর উত্তরে বলছেন: 'অন্যথায়' ইত্যাদি, অর্থাৎ গুণসমূহ থেকে ভিন্ন (পরমেশ্বরের) কর্তৃত্ব না মানলে। মোক্ষধর্মে পরমেশ্বরের কর্তৃত্ব বলা হয়েছে, তার সাথে বিরোধ ঘটবে — এটি বাক্যশেষ।",
            "ka": "।।೧೪.೧೯ -- ೧೪.೨೦।। 'ಗುಣಗಳ ಹೊರತು ಬೇರೆ ಕರ್ತನಿಲ್ಲ...' - ಇಲ್ಲಿ ಗುಣಗಳಿಗೇ ಸ್ವತಂತ್ರ ಕರ್ತೃತ್ವವಿದೆಯೇ ಹೊರತು ಮತ್ತಾರಿಗೂ ಇಲ್ಲ ಎಂಬ ಅಪವ್ಯಾಖ್ಯಾನವನ್ನು ನಿರಾಕರಿಸಲು ಹೇಳುತ್ತಾರೆ: 'ಪರಿಣಾಮಿ' ಇತ್ಯಾದಿ. ಇದು ಏಕೆ? ಎಂದರೆ ಹೇಳುತ್ತಾರೆ: 'ಅನ್ಯಥಾ' ಇತ್ಯಾದಿ, ಅಂದರೆ ಗುಣಗಳಿಗಿಂತ ಭಿನ್ನವಾದ (ಪರಮೇಶ್ವರನ) ಕರ್ತೃತ್ವವನ್ನು ಒಪ್ಪದಿಿದ್ದರೆ. ಮೋಕ್ಷಧರ್ಮದಲ್ಲಿ ಪರಮೇಶ್ವರನ ಕರ್ತೃತ್ವವನ್ನು ಹೇಳಲಾಗಿದೆ, ಅದಕ್ಕೆ ವಿರೋಧವುಂಟಾಗುತ್ತದೆ - ಎಂಬುದು ವಾಕ್ಯಶೇಷ.",
            "sa": "।।14.19 -- 14.20।।नान्यं गुणेभ्यः कर्तारं इति स्वतन्त्रकर्तृत्वं गुणानामेव? नान्यस्येत्युच्यत इत्यपव्याख्याननिरासार्थमाह -- परिणामीति। कुत एतत् इत्यत आह -- अन्यथेति गुणेभ्योऽन्यस्य कर्तृत्वाभावे। मोक्षधर्मे परमेश्वरस्य कर्तृत्वमुक्तं तद्विरोधश्चेति वाक्यशेषः।"
        }
    },
    "vallabh": {
        "author": "Sri Vallabhacharya",
        "commentary": {
            "hi": "।।14.19 -- 14.20।। इस प्रकार गुणों के सर्ग-भेद के कथन में समस्त जीव की बंधन-लीला का निरूपण करके, अब उनके विवेक से गुणातीतता के द्वारा मोक्ष-लीला का कथन दो श्लोकों में करते हैं: 'नान्यम्' इत्यादि। जब साधक गुणों से भिन्न (अन्य प्राकृतिक) कर्ता नहीं देखता, केवल गुण ही अपनी-अपनी प्रवृत्तियों में कर्ता हैं—ऐसा देखता है और गुणों से परे परमात्मा को जानता है, तब द्रष्टा 'मेरे भाव' अर्थात् अक्षरब्रह्म-भाव को प्राप्त होता है; क्योंकि श्रुति कहती है—'ब्रह्मवित् ब्रह्मैव भवति' (मुण्डक उपनिषद् 3.2.9)। निर्गुण ब्रह्म स्वयं अव्यय है; तब इन तीनों गुणों का अतिक्रमण करके वह अमृत को प्राप्त करता है अर्थात् ब्रह्मसुख का उपभोग करता है।",
            "en": "14.19 -- 14.20 Thus having explained the pastime of bondage (bandha-lila) for all embodied beings through the description of the modifications of the Gunas, he now states in two verses the pastime of liberation (moksha-lila) through the transcendence of the Gunas born of discrimination: 'Nanyam...' etc. When the seer beholds no other agent than the Gunas in their respective functions, and knows the Supreme Lord as distinct from and beyond the Gunas, then the seer attains My nature, i.e., the state of Akshara Brahman. For the Shruti states: 'The knower of Brahman becomes Brahman indeed' (Mundaka Upanishad 3.2.9). Indeed, Brahman is beyond attributes and imperishable; then transcending these three Gunas, he attains immortality, i.e., enjoys the bliss of Brahman.",
            "be": "।।১৪.১৯ -- ১৪.২০।। এইভাবে গুণের স্বর্গ-ভেদের কথনে সমস্ত জীবের বন্ধন-লীলা প্রতিপাদন করে, এখন তাদের বিবেকের দ্বারা গুণাতীততার মাধ্যমে মোক্ষ-লীলা দুটি শ্লোকে বলছেন: 'নান্যম্' ইত্যাদি। যখন সাধক গুণসমূহ ছাড়া অন্য কোনো (প্রাকৃতিক) কর্তাকে দেখে না, কেবল গুণগুলিই নিজ নিজ প্রবৃত্তিতে কর্তা — এরূপ দেখে এবং গুণসমূহ থেকে পরে পরমাত্মাকে জানে, তখন দ্রষ্টা 'আমার ভাব' অর্থাৎ অক্ষরব্রহ্ম-ভাব প্রাপ্ত হন; কারণ শ্রুতি বলে — 'ব্রহ্মবিৎ ব্রহ্মৈব ভবতি' (মুণ্ডক উপনিষদ্ ৩.২.৯)। নির্গুণ ব্রহ্ম স্বয়ং অব্যয়; তখন এই তিনটি গুণকে অতিক্রম করে তিনি অমৃত লাভ করেন অর্থাৎ ব্রহ্মসুখ ভোগ করেন।",
            "ka": "।।೧೪.೧೯ -- ೧೪.೨೦।। ಹೀಗೆ ಗುಣಗಳ ಸೃಷ್ಟಿ-ಭೇದದ ಕಥನದಲ್ಲಿ ಸಮಸ್ತ ಜೀವಿಗಳ ಬಂಧನ-ಲೀಲೆಯನ್ನು ಪ್ರತಿಪಾದಿಸಿ, ಈಗ ಅವುಗಳ ವಿವೇಕದಿಂದ ಗುಣಾತೀತತೆಯ ಮೂಲಕ ಮೋಕ್ಷ-ಲೀಲೆಯನ್ನು ಎರಡು ಶ್ಲೋಕಗಳಲ್ಲಿ ಹೇಳುತ್ತಾರೆ: 'ನಾನ್ಯಮ್' ಇತ್ಯಾದಿ. ಸಾಧಕನು ಗುಣಗಳಿಗಿಂತ ಭಿನ್ನವಾದ (ಪ್ರಾಕೃತಿಕ) ಕರ್ತನನ್ನು ಕಾಣದೆ, ಗುಣಗಳೇ ತಮ್ಮ ತಮ್ಮ ಪ್ರವೃತ್ತಿಗಳಲ್ಲಿ ಕರ್ತೃಗಳಾಗಿವೆ ಎಂದು ಕಾಣುತ್ತಾನೋ ಮತ್ತು ಗುಣಗಳಿಗಿಂತ ಪರವಾಗಿರುವ ಪರಮಾತ್ಮನನ್ನು ತಿಳಿಯುತ್ತಾನೋ, ಆಗ ದ್ರಷ್ಟೃವು 'ನನ್ನ ಭಾವ' ಅಂದರೆ ಅಕ್ಷರಬ್ರಹ್ಮ-ಭಾವವನ್ನು ಪಡೆಯುತ್ತಾನೆ; ಏಕೆಂದರೆ ಶೃತಿಯು ಹೇಳುತ್ತದೆ - 'ಬ್ರಹ್ಮವಿತ್ ಬ್ರಹ್ಮೈವ ಭವತಿ' (ಮುಂಡಕೋಪನಿಷತ್ ೩.೨.೯). ನಿರ್ಗುಣ ಬ್ರಹ್ಮನು ಸ್ವತಃ ಅವ್ಯಯನು; ಆಗ ಈ ಮೂರು ಗುಣಗಳನ್ನು ಮೀರಿ ಅವನು ಅಮೃತವನ್ನು ಪಡೆಯುತ್ತಾನೆ ಅಂದರೆ ಬ್ರಹ್ಮಾನಂದವನ್ನು ಅನುಭವಿಸುತ್ತಾನೆ.",
            "sa": "।।14.19 -- 14.20।।एवं गुणसर्गभेदोक्तौ पुरुषस्य सर्वस्य बन्धलीलामुपपाद्येदानीं तद्विवेकतो गुणात्ययद्वारा मोक्षलीलामाहू द्वाभ्याम् -- नान्यमिति। यदा गुणेभ्योऽन्यं कर्त्तारं नानुपश्यति गुणा एव स्वानुगुणप्रवृत्तिषु कर्त्तार इति पश्यति गुणेभ्यश्च परमात्मानं वेत्ति तदा द्रष्टा मद्भावं ब्रह्माक्षरभावं प्राप्नोति ब्रह्मवित् (ब्रह्म वेद) ब्रह्मैव भवति [मुं.उ.3।2।9] इति श्रुतेः। निर्गुणं हि ब्रह्म स्वयमव्ययं तदा गुणांस्त्रीनेतानतीत्यामृतमश्नुते प्राप्नुते ब्रह्मसुखं वा भुङ्क्ते।"
        }
    },
    "ms": {
        "author": "Sri Madhusudan Saraswati",
        "commentary": {
            "hi": "।।14.20।। कैसे प्राप्त होता है, यह कहते हैं — मायात्मक सत्त्व, रज और तम नाम वाले, देह की उत्पत्ति के बीजभूत इन तीनों गुणों का जीवित रहते हुए ही तत्त्वज्ञान द्वारा बाध (अतिक्रमण) करके, जन्म, मृत्यु, जरा और आध्यात्मिक आदि मायामय दुःखों से जीवित रहते हुए ही संबंध-रहित होकर, विद्वान् अमृत स्वरूप मोक्ष अर्थात् मेरे भाव को अंत में प्राप्त करता है।",
            "en": "14.20 How does he attain it? He explains—having transcended, even while living, through the knowledge of Reality, these three Gunas named Sattva, Rajas, and Tamas, which are of the nature of Maya and are the seeds of origin of the body; being freed even in this life from connection with birth, death, old age, and the illusory sorrows such as adhyatmika (intra-organic), the enlightened person ultimately attains immortality, which is liberation, My very Being.",
            "be": "।।১৪.২০।। কীভাবে প্রাপ্ত হন, তা বলছেন — মায়াত্মক সত্ত্ব, রজ ও তম নামক, দেহের উৎপত্তির বীজস্বরূপ এই তিনটি গুণকে জীবিত থাকতেই তত্ত্বজ্ঞানের দ্বারা বাধ্য (অতিক্রান্ত) করে, জন্ম, মৃত্যু, জরা এবং আধ্যাত্মিক আদি মায়াময় দুঃখসমূহ থেকে জীবিত অবস্থাতেই সম্বন্ধরহিত হয়ে, বিদ্বান অমৃতস্বরূপ মোক্ষ অর্থাৎ আমার ভাব অন্তে প্রাপ্ত হন।",
            "ka": "।।೧೪.೨೦।। ಹೇಗೆ ತಲುಪುತ್ತಾನೆ ಎಂದರೆ ಹೇಳುತ್ತಾರೆ - ಮಾಯಾತ್ಮಕವಾದ ಸತ್ತ್ವ, ರಜಸ್ ಮತ್ತು ತಮಸ್ ಎಂಬ ಹೆಸರಿನ, ಶರೀರದ ಉತ್ಪತ್ತಿಗೆ ಬೀಜವಾದ ಈ ಮೂರು ಗುಣಗಳನ್ನು ಜೀವಂತವಾಗಿದ್ದಾಗಲೇ ತತ್ತ್ವಜ್ಞಾನದಿಂದ ಮೀರಿದವನಾಗಿ; ಜನ್ಮ, ಮೃತ್ಯು, ಮುಪ್ಪು ಮತ್ತು ಆಧ್ಯಾತ್ಮಿಕಾದಿ ಮಾಯಾಮಯ ದುಃಖಗಳಿಂದ ಜೀವಂತವಾಗಿದ್ದಾಗಲೇ ಸಂಬಂಧರಹಿತನಾಗಿ, ಜ್ಞಾನಿಯು ಅಮೃತಸ್ವರೂಪವಾದ ಮೋಕ್ಷವನ್ನು ಅಂದರೆ ನನ್ನ ಭಾವವನ್ನು ಕೊನೆಯಲ್ಲಿ ಪಡೆಯುತ್ತಾನೆ.",
            "sa": "।।14.20।।कथमधिगच्छतीत्युच्यते -- गुणानेतान्मायात्मकांस्त्रीन्सत्त्वरजस्तमोनाम्नः देहसमुद्भवान्देहोत्पत्तिबीजभूतान् अतीत्य जीवन्नेव तत्त्वज्ञानेन (नाधिगत्य) बाधित्वा जन्ममृत्युजरादुःखैर्जन्मना,मृत्युना जरया दुःखैश्चाध्यात्मिकादिभिर्मायामयैर्विमुक्तो जीवन्नेव तत्संबन्धशून्यः सन् विद्वानमृतं मोक्षं मद्भावमन्ते प्राप्नोति।"
        }
    },
    "srid": {
        "author": "Sri Sridhara Swami",
        "commentary": {
            "hi": "।।14.20।। और तब गुणों द्वारा उत्पन्न समस्त अनर्थों की निवृत्ति से कृतार्थ हो जाता है—यह कहते हैं: 'गुणान्' इत्यादि। देहादि आकार में जिनका समुद्भव (परिणाम) होता है, वे 'देहसमुद्भव' हैं। इन तीनों गुणों का अतिक्रमण करके, उनके द्वारा किए गए जन्मादि से विमुक्त हुआ पुरुष अमृत का अनुभव करता है अर्थात् ब्रह्मानन्द को प्राप्त करता है।",
            "en": "14.20 And then, by the cessation of all evils caused by the Gunas, he becomes fulfilled in purpose—thus he says: 'Gunan...' etc. 'Dehasamudbhavah' means those whose transformation is in the form of the body etc. Having transcended even all these three Gunas and being freed from birth etc. caused by them, he experiences immortality, i.e., attains the bliss of Brahman.",
            "be": "।।১৪.২০।। এবং তখন গুণসমূহের দ্বারা কৃত সমস্ত অনর্থের নিবৃত্তির মাধ্যমে কৃতার্থ হন — এই কথা বলছেন: 'গুণান্' ইত্যাদি। দেহাি আকারে যাদের সমুদ্ভব (পরিণাম) হয়, তারা 'দেহসমুদ্ভব'। এই তিনটি গুণকেও অতিক্রম করে, এদের দ্বারা সৃষ্ট জন্মাি থেকে মুক্ত হয়ে তিনি অমৃত অনুভব করেন অর্থাৎ ব্রহ্মানন্দ লাভ করেন।",
            "ka": "।।೧೪.೨೦।। ಮತ್ತು ಆಗ ಗುಣಗಳಿಂದ ಉಂಟಾಗುವ ಸಮಸ್ತ ಅನರ್ಥಗಳ ನಿವೃತ್ತಿಯಿಂದ ಕೃತಾರ್ಥನಾಗುತ್ತಾನೆ - ಎಂದು ಹೇಳುತ್ತಾರೆ: 'ಗುಣಾನ್' ಇತ್ಯಾದಿ. ದೇಹಾದಿ ಆಕಾರದಲ್ಲಿ ಯಾವುದರ ಪರಿಣಾಮವಿದೆಯೋ ಅವು 'ದೇಹಸಮುದ್ಭವ'. ಈ ಮೂರೂ ಗುಣಗಳನ್ನು ಮೀರಿ, ಅವುಗಳಿಂದ ಉಂಟಾಗುವ ಜನ್ಮಾದಿಗಳಿಂದ ವಿಮುಕ್ತನಾಗಿ ಅಮೃತತ್ವವನ್ನು ಅನುಭವಿಸುತ್ತಾನೆ ಅಂದರೆ ಬ್ರಹ್ಮಾನಂದವನ್ನು ಪಡೆಯುತ್ತಾನೆ.",
            "sa": "।।14.20।।ततश्च गुणकृतसर्वानर्थनिवृत्त्या कृतार्थो भवतीत्याह -- गुणानिति। देहाद्याकारः समुद्भवः परिणामो येषां ते देहसमुद्भवाः तानेतांस्त्रीनपि गुणानतीत्यातिक्रम्य तत्कृतैर्जन्मादिभिर्विमुक्तः सन्नमृतमश्नुते ब्रह्मानन्दं प्राप्नोति।"
        }
    },
    "dhan": {
        "author": "Sri Dhanpati",
        "commentary": {
            "hi": "।।14.20।। 'कैसा प्राप्त होता है?' इस आकांक्षा पर कहते हैं। यथोक्त मायात्मक सत्त्व, रज और तम नामक इन तीनों गुणों से 'उत्पन्न होते हैं' इसलिए जो देह की उत्पत्ति के कारण (बीज) हैं, उन देहसमुद्भव गुणों का देही विद्वान् जीवित रहते ही अतिक्रमण करके; जन्म, मृत्यु, जरा और दुःखों से जीवन्मुक्त होकर, सर्व-अनर्थ-रहित होकर अमृत अर्थात् ब्रह्मानन्द, मद्भाव मोक्ष को प्राप्त करता है—यह अर्थ है।",
            "en": "14.20 In response to the query 'How does he attain it?', he states—the embodied wise person, having transcended even while living these three Gunas named Sattva, Rajas, and Tamas, which are Maya-natured and are the cause (seed) of the birth of the body ('dehasamudbhavan'); becoming liberated while living from birth, death, old age, and sorrows, and completely freed from all evils, attains immortality, which means the bliss of Brahman, My state, liberation—this is the meaning.",
            "be": "।।১৪.২০।। 'কীভাবে প্রাপ্ত হন?' এই প্রশ্নের উত্তরে বলছেন — যথোক্ত মায়াত্মক সত্ত্ব, রজ ও তম নামক এই তিনটি গুণ থেকে 'উৎপন্ন হয়' তাই যা দেহের উৎপত্তির কারণ (বীজ), সেই দেহসমুদ্ভব গুণসমূহকে দেহী বিদ্বান জীবিত থাকতেই অতিক্রম করে; জন্ম, মৃত্যু, জরা ও দুঃখ থেকে জীবন্মুক্ত হয়ে, সর্ব-অনর্থ-মুক্ত হয়ে অমৃত অর্থাৎ ব্রহ্মানন্দ, মদ্ভাব মোক্ষ লাভ করেন — এটাই অর্থ।",
            "ka": "।।೧೪.೨೦।। 'ಹೇಗೆ ತಲುಪುತ್ತಾನೆ?' ಎಂಬ ಅಪೇಕ್ಷೆಗೆ ಹೇಳುತ್ತಾರೆ. ಯಥೋಕ್ತವಾದ ಮಾಯಾತ್ಮಕ ಸತ್ತ್ವ, ರಜಸ್ ಮತ್ತು ತಮಸ್ ಎಂಬ ಮೂರು ಗುಣಗಳಿಂದ 'ಹುಟ್ಟುತ್ತವೆ' ಆದ್ದರಿಂದ ಶರೀರದ ಉತ್ಪತ್ತಿಗೆ ಕಾರಣವಾದ (ಬೀಜವಾದ) ಆ ದೇಹಸಮುದ್ಭವ ಗುಣಗಳನ್ನು ದೇಹಿಯಾದ ಜ್ಞಾನಿಯು ಜೀವಂತವಾಗಿದ್ದಾಗಲೇ ಮೀರಿ; ಜನ್ಮ, ಮೃತ್ಯು, ಮುಪ್ಪು ಮತ್ತು ದುಃಖಗಳಿಂದ ಜೀವನ್ಮುಕ್ತನಾಗಿ, ಸರ್ವ-ಅನರ್ಥ-ರಹಿತನಾಗಿ ಅಮೃತ ಅಂದರೆ ಬ್ರಹ್ಮಾನಂದ, ಮದ್ಭಾವ ಮೋಕ್ಷವನ್ನು ಪಡೆಯುತ್ತಾನೆ ಎಂದರ್ಥ.",
            "sa": "।।14.20।।कथमधिगच्छतीत्यपेक्षायमाह। गुणानेतान्यथोक्तान्मायात्मकांस्त्रीन्सत्त्वरजस्तमःसंज्ञकान् समुद्भवन्त्येभ्य इति समुद्भवाः देहस्य समुद्भवाः तान् देहसमुद्भवान् तान् देहसमुद्धवान् देहोत्पत्तिबीजभूतान् देही अतीत्य विद्वान्,जीवन्नेवातिक्रम्य जन्ममृत्युजरादुःखै जन्म च मृत्युश्च जरा च दुःखानि च तैः जीवन्नेव मुक्तः सर्वानर्थविनिर्मुक्तः अमृतं ब्रह्मानन्दं मद्भावं मोक्षमश्रुते प्राप्तोतीत्यर्थः।"
        }
    },
    "venkat": {
        "author": "Vedantadeshikacharya Venkatanatha",
        "commentary": {
            "hi": "।।14.20।। इस प्रकार अनेक श्रुति-स्मृति आदि के विरुद्ध मुक्त जीव की 'भगवत्ता' (ईश्वरत्व) कैसे कही गई है—ऐसी शंका होने पर पूर्वोक्त अर्थ का अनुवाद करके अगले श्लोक का अवतरण देते हैं: 'वह भगवद्भाव कैसा है?'। 'देहसमुद्भवान्' पद में 'देहोत्पत्तिबीजभूतान्' (दूसरों द्वारा की गई व्याख्या) अयुक्त है, क्योंकि 'गुणाः प्रकृतिसम्भवाः' (14.5) की भाँति यहाँ भी प्रकृति-परिणाम-रूप देह के आश्रयत्व का वचन ही युक्त है; इसी अभिप्राय से कहते हैं: 'देहाकार-परिणत-प्रकृति-समुद्भवान्'। आगे कहे जाने वाले प्रकार से गुणों का अतिक्रमण बद्ध दशा में ही होता है—यह कहते हैं: 'गुणान् अतीत्य तेभ्यः अन्यम्' इत्यादि से। 'जन्ममृत्युजरादुःखैः' का अर्थ है जन्मादि द्वारा किए गए दुःखों से। अथवा जन्मादि और उनसे साध्य दुःखों से। 'मद्भावं सोऽधिगच्छति' (14.19) में कहे गए अर्थ को ही 'विमुक्तोऽमृतमश्नुते' से स्पष्ट किया गया है—यह बताते हुए कहते हैं: 'आत्मानम् अनुभवति'। 'एष मद्भावः' का अर्थ है—यह भगवद्भाव श्रुति आदि के विरुद्ध नहीं है।",
            "en": "14.20 Thus, raising the objection how the state of being God (Bhagavattva) of a liberated soul is declared when it contradicts numerous Shrutis and Smritis, he translates the previously stated meaning and introduces the next verse: 'What is that Divine state (Bhagavad-bhava) like?' In the phrase 'dehasamudbhavan', the commentary by others as 'being the seeds of origin of the body' is improper, because just as in 'gunah prakriti-sambhavah' (14.5), here too declaring their abiding in the body transformed from Prakriti is appropriate; with this intention he explains it as 'arising from Prakriti transformed into the form of the body'. The transcendence of the Gunas in the manner to be stated occurs while still in the bound state itself—he shows this with 'gunan atitya...' etc. 'Janma-mrtyu-jara-duhkhaih' means freed from sorrows produced by birth etc., or from birth etc. and the sorrows caused by them. What was stated in 'madbhavam so'dhigacchati' (14.19) is explained by 'vimukto'mrtam asnute'—showing this, he says 'experiences the Self'. 'Esah madbhavah' means this state is not contrary to Shruti texts.",
            "be": "।।১৪.২০।। এইভাবে একাধিক শ্রুতি-স্মৃতি ইত্যাদির বিরুদ্ধে মুক্ত জীবের 'ভগবত্তা' (ঈশ্বরত্ব) কীভাবে বলা হলো — এরূপ আশঙ্কা হলে পূর্বোক্ত অর্থের অনুবাদ করে পরবর্তী শ্লোক অবতরণ করছেন: 'সেই ভগবদ্ভাব কেমন?'। 'দেহসমুদ্ভবান্' পদে 'দেহের উৎপত্তির বীজস্বরূপ' (অন্যদের করা ব্যাখ্যা) অযৌক্তিক, কারণ 'গুণাঃ প্রকৃতিসম্ভবাঃ' (১৪.৫)-এর মতো এখানেও প্রকৃতি-পরিণাম-রূপ দেহের আশ্রয়ত্বের বাক্যই যুক্তিসঙ্গত; এই অভিপ্রায়ে বলছেন: 'দে আকারে পরিণত প্রকৃতি থেকে উৎপন্ন'। পরবর্তীতে বলা প্রકારે গুণের অতিক্রম বদ্ধ দশাতেই হয় — এটি বলছেন: 'গুণান্ অতীত্য় তেভ্যঃ অন্যম্' ইত্যাদি দিয়ে। 'জন্মমৃত্যুজরাদুঃখৈঃ'-এর অর্থ জন্মাি দ্বারা সৃষ্ট দুঃখসমূহ থেকে। অথবা জন্মাি এবং তা থেকে সাধ্য দুঃখসমূহ থেকে। 'মদ্ভাবং সোঽধিগচ্ছতি' (১৪.১৯)-তে বলা অর্থকেই 'বিমুক্তোঽমৃতমশ্নুতে' দিয়ে স্পষ্ট করা হয়েছে — এটি দেখিয়ে বলছেন: 'আত্মানম্ অনুভবতি'। 'এষ মদ্ভাবঃ'-এর অর্থ — এই ভগবদ্ভাব শ্রুতি আদির বিরুদ্ধে নয়।",
            "ka": "।।೧೪.೨೦।। ಹೀಗೆ ಅನೇಕ ಶೃತಿ-ಸ್ಮೃತಿ ಮುಂತಾದವುಗಳಿಗೆ ವಿರುದ್ಧವಾಗಿ ಮುಕ್ತ ಜೀವಿಯ 'ಭಗವತ್ತಾ' (ಈಶ್ವರತ್ವ) ಹೇಗೆ ಹೇಳಲ್ಪಟ್ಟಿದೆ - ಎಂಬ ಶಂಕೆಯುಂಟಾಗಲು, ಪೂರ್ವರೂಪದ ಅರ್ಥವನ್ನು ಅನುವಾದಿಸಿ ಮುಂದಿನ ಶ್ಲೋಕವನ್ನು ಪರಿಚಯಿಸುತ್ತಾರೆ: 'ಆ ಭಗವದ್ಭಾವವು ಎಂತಹುದು?'. 'ದೇಹಸಮುದ್ಭವಾನ್' ಎಂಬಲ್ಲಿ 'ದೇಹೋತ್ಪತ್ತಿಬೀಜಭೂತಾನ್' (ಇತರರ ವ್ಯಾಖ್ಯಾನ) ಅಯುಕ್ತವಾಗಿದೆ, ಏಕೆಂದರೆ 'ಗುಣಾಃ ಪ್ರಕೃತಿಸಂಭವಾಃ' (೧೪.೫) ಎಂಬಂತೆ ಇಲ್ಲಿಯೂ ಪ್ರಕೃತಿಯ ಪರಿಣಾಮ ರೂಪವಾದ ದೇಹದ ಆಶ್ರಯತ್ವದ ವಚನವೇ ಯುಕ್ತವಾಗಿದೆ; ಈ ಅಭಿಪ್ರಾಯದಿಂದ ಹೇಳುತ್ತಾರೆ: 'ದೇಹಾಕಾರಪರಿಣತಪ್ರಕೃತಿಸಮುದ್ಭವಾನ್'. ಮುಂದೆ ಹೇಳಲಾಗುವ ರೀತಿಯಲ್ಲಿ ಗುಣಗಳ ಅತಿಕ್ರಮಣವು ಬದ್ಧ ದಶೆಯಲ್ಲಿಯೇ ಆಗುತ್ತದೆ - ಎಂಬುದನ್ನು ಹೇಳುತ್ತಾರೆ: 'ಗುಣಾನ್ ಅತ್ಯೀತ್ಯ ತೇಭ್ಯಃ ಅನ್ಯಮ್' ಇತ್ಯಾದಿಯಿಂದ. 'ಜನ್ಮಮೃತ್ಯುಜರಾದುಃಖೈಃ' ಎಂದರೆ ಜನ್ಮಾದಿಗಳಿಂದ ಉಂಟಾದ ದುಃಖಗಳಿಂದ. ಅಥವಾ ಜನ್ಮಾದಿಗಳು ಮತ್ತು ಅವುಗಳಿಂದ ಸಾಧ್ಯವಾಗುವ ದುಃಖಗಳಿಂದ. 'ಮದ್ಭಾವಂ ಸೋಽಧಿಗಚ್ಛತಿ' (೧೪.೧೯) ರಲ್ಲಿ ಹೇಳಿದ ಅರ್ಥವನ್ನೇ 'ವಿಮುಕ್ತೋಽಮೃತಮಶ್ನುತೇ' ಎಂಬುದರಿಂದ ಸ್ಪಷ್ಟಪಡಿಸಲಾಗಿದೆ - ಎಂಬುದನ್ನು ತೋರಿಸುತ್ತಾ ಹೇಳುತ್ತಾರೆ: 'ಆತ್ಮಾನಮ್ ಅನುಭವತಿ'. 'ಏಷ मद्ಭಾವಃ' ಎಂದರೆ - ಈ ಭಗವದ್ಭಾವವು ಶೃತ್ಯಾದಿಗಳಿಗೆ ವಿರುದ್ಧವಲ್ಲ ಎಂದರ್ಥ.",
            "sa": "।।14.20।।तदेवमनेकश्रुतिस्मृत्यादिविरुद्धं मुक्तस्य भगवत्त्वं कथमुच्यते इति शङ्कायामुक्तमर्थं कर्तृभ्य इत्यादिनानूद्यानन्तरश्लोकमवतारयति -- स भगवद्भावः कीदृश इति।देहसमुद्भवान् इत्यत्र देहोत्पत्तिबीजभूतानिति परव्याख्यानमयुक्तम्?गुणाः प्रकृतिसम्भवाः [14।5] इतिवदत्रापि प्रकृतिपरिणतिरूपदेहाश्रयत्ववचनस्य युक्तत्वादित्यभिप्रायेणाहदेहाकारपरिणतप्रकृतिसमुद्भवानिति। वक्ष्यमाणप्रकारेण गुणात्ययो बद्धदशायामेवेत्याहगुणानतीत्य तेभ्योऽन्यमित्यादिना।जन्ममृत्युजरादुःखैः? जन्मादिकृतैर्दुःखैरित्यर्थः। जन्मादिभिस्तत्साध्यैश्च दुःखैरिति वा।मद्भावं सोऽधिगच्छति [14।19] इत्युक्तमेवविमुक्तोऽमृतमश्नुते इत्यनेन विवृतमित्याहआत्मानमनुभवतीति।एष मद्भाव इत्यर्थ इति -- एष इति न पुनः श्रुत्यादिविरुद्ध इत्यर्थः।"
        }
    },
    "puru": {
        "author": "Sri Purushottamji",
        "commentary": {
            "hi": "।।14.20।। तब मेरे भाव से युक्त होकर गुण-दोषों से अभिभूत नहीं होता—यह कहते हैं: 'गुणानेतान्' इत्यादि। देही जीव देह की उत्पत्ति के कारणभूत इन लौकिक (अलौकिक नहीं) तीनों गुणों का अतिक्रमण करके; जन्म जो कर्म-भोग के लिए है, मृत्यु जो उस भोग की समाप्ति अथवा भगवान के विस्मरण रूप है, जरा जो सेवा में प्रतिबन्ध रूप है, दुःख जो संसारात्मक है—इनसे विमुक्त होकर अमृत अर्थात् मरण आदि दोषों से रहित लौकिक देह का उपभोग/प्राप्ति करता है—यह अर्थ है। अथवा अमृत अलौकिक देह को प्राप्त करके मेरे साथ समस्त कामनाओं को भोगता है, जैसा कि श्रुति कहती है 'सोऽश्नुते सर्वान् कामान् सह' (तैत्तिरीय उपनिषद् 2.1)—इस रीति से 'देही' पद से यह व्यंजित होता है, अन्यथा देहवत् पद व्यर्थ हो जाएगा—यह भाव है।",
            "en": "14.20 Then, being endowed with My state, he is not overcome by the defects of the Gunas—thus he states: 'Gunanetān...' etc. The embodied jiva, having transcended these worldly (not divine) three Gunas which are the origin of bodies; being freed from birth meant for enjoying karma, death which is the end of that enjoyment or forgetfulness of the Lord, old age which is an obstacle to devotional service, and sorrow which is of the nature of worldly samsara—experiences/attains immortality, i.e., a body free from defects like death. Or, attaining an immortal divine body, he enjoys all desires together with Me, according to the Shruti: 'He enjoys all desires together with Brahman' (Taittiriya Upanishad 2.1)—this is implied by the word 'dehi', otherwise the word denoting embodiment would be meaningless; this is the intention.",
            "be": "।।১৪.২০।। তখন আমার ভাবে যুক্ত হয়ে গুণ-দোষের দ্বারা অভিভূত হন না — এই কথা বলছেন: 'গুণানেতান্' ইত্যাদি। দেহী জীব দেহের উৎপত্তির কারণস্বরূপ এই লৌকিক (অলৌকিক নয়) তিনটি গুণকে অতিক্রম করে; জন্ম যা কর্মভোগের জন্য, মৃত্যু যা সেই ভোগের সমাপ্তি বা ভগবদ্বিস্মরণের রূপ, জরা যা সেবায় প্রতিবন্ধকস্বরূপ, দুঃখ যা সংসারাাত্মক — এরা থেকে মুক্ত হয়ে অমৃত অর্থাৎ মরণ আদি দোষরহিত লৌকিক দেহ ভোগ/প্রাপ্ত হন — এটাই অর্থ। অথবা অমৃত অলৌকিক দেহ প্রাপ্ত হয়ে আমার সাথে সমস্ত কামনা ভোগ করেন, যেমন শ্রুতি বলে 'সোঽশ্নুতে সর্বান্ কামান্ সহ' (তৈত্তিরীয় উপনিষদ্ ২.১) — এই রীতির দ্বারা 'দেহী' পদের মাধ্যমে এটি ব্যঞ্জিত হয়, অন্যথায় দেহবৎ পদ ব্যর্থ হয়ে যাবে — এটাই ভাব।",
            "ka": "।।೧೪.೨೦।। ಆಗ ನನ್ನ ಭಾವದಿಂದ ಯುಕ್ತನಾಗಿ ಗುಣ-ದೋಷಗಳಿಂದ ಅಭಿಭೂತನಾಗುವುದಿಲ್ಲ - ಎಂದು ಹೇಳುತ್ತಾರೆ: 'ಗುಣಾನೇತಾನ್' ಇತ್ಯಾದಿ. ದೇಹಿಯಾದ ಜೀವನು ದೇಹಗಳ ಉತ್ಪತ್ತಿಗೆ ಕಾರಣವಾದ ಈ ಲೌಕಿಕ (ಅಲೌಕಿಕವಲ್ಲದ) ಮೂರು ಗುಣಗಳನ್ನು ಮೀರಿ; ಕರ್ಮಭೋಗಕ್ಕಾಗಿ ಇರುವ ಜನ್ಮ, ಆ ಭೋಗದ ಸಮಾಪ್ತಿ ಅಥವಾ ಭಗವದ್ವಿಸ್ಮರಣೆಯ ರೂಪದ ಮೃತ್ಯು, ಸೇವೆಯಲ್ಲಿ ಪ್ರತಿಬಂಧಕ ರೂಪದ ಮುಪ್ಪು, ಸಂಸಾರಾತ್ಮಕವಾದ ದುಃಖ - ಇವುಗಳಿಂದ ವಿಮುಕ್ತನಾಗಿ ಅಮೃತ ಅಂದರೆ ಮರಣಾದಿ ದೋಷರಹಿತ ಲೌಕಿಕ ದೇಹವನ್ನು ಅನುಭವಿಸುತ್ತಾನೆ/ಪಡೆಯುತ್ತಾನೆ ಎಂದರ್ಥ. ಅಥವಾ ಅಮೃತ ಅಲೌಕಿಕ ದೇಹವನ್ನು ಪಡೆದು ನನ್ನೊಂದಿಗೆ ಸಮಸ್ತ ಕಾಮಗಳನ್ನು ಅನುಭವಿಸುತ್ತಾನೆ, 'ಸೋಽಶ್ನುತೇ ಸರ್ವಾನ್ ಕಾಮಾನ್ ಸಹ' (ತೈತ್ತಿರೀಯ ಉಪನಿಷತ್ ೨.೧) ಎಂಬ ಶೃತಿವಾಕ್ಯದಂತೆ - ಈ ರೀತಿಯಾಗಿ 'ದೇಹೀ' ಎಂಬ ಪದದಿಂದ ಇದು ವ್ಯಂಜಿತವಾಗುತ್ತದೆ, ಇಲ್ಲದಿದ್ದರೆ ದೇಹವತ್ ಎಂಬ ಪದವು ವ್ಯರ್ಥವಾಗುತ್ತದೆ ಎಂಬುದು ಭಾವ.",
            "sa": "।।14.20।।ततो मद्भावयुक्तो गुणदोषाभिभूतो न भवतीत्याह -- गुणानेतानिति। देही जीवो देहसमुद्भवान् देहानां समुद्भव उत्पत्तिर्येभ्यस्तादृशानेतान् लौकिकान् न त्वलौकिकान् त्रीन् गुणानतीत्य अतिक्रम्य? जन्म तत्कर्मभोगार्थकं? मृत्युस्तद्भोगसमाप्तिरूपो भगवद्विस्मरणरूपो वा? जरा सेवाप्रतिबन्धरूपा? दुःखं संसारात्मकम्? एतैर्विमुक्तः अमृतं मरणादिदोषरहितम् लौकिकं देहमश्नुते भुङ्क्ते प्राप्नोतीत्यर्थः। अथवा अमृतमलौकिकं देहं प्राप्य मया सह सर्वकामानश्नुते सोऽश्नुते सर्वान् कामान् सह [तै.उ.2।1] इति श्रुत्युक्तरीत्या देहीतिपदादिदं व्यज्यते अन्यथा देहवत्पदं व्यर्थं स्यादिति भावः।"
        }
    },
    "neel": {
        "author": "Sri Neelkanth",
        "commentary": {
            "hi": "।।14.20।। 'आपके भाव को कैसे प्राप्त होता है?'—इस पर कहते हैं: 'गुणान्' इत्यादि। महदादि तेईस विकारों के रूप में परिणत, स्थूल शरीर की उत्पत्ति के कारणभूत इन गुणों का जीवित रहते ही निर्विकल्पक समाधि के अभ्यास द्वारा अतिक्रमण (बाध) करके अमृत अर्थात् मोक्ष को प्राप्त करता है। इससे आनन्द की प्राप्ति को गुणातीतता का प्रयोजन बताया गया है। और 'जन्ममृत्युजरादुःखैः विमुक्तः सन्' इससे अनर्थ की निवृत्ति कही गई है।",
            "en": "14.20 'How does he attain Your state?'—to this he says: 'Gunan...' etc. Transcending even while living these Gunas which are transformed into the twenty-three evolutes starting with Mahat and are the origin of the gross body, by subduing them through the practice of nirvikalpa samadhi, he attains immortality, i.e., liberation. By this, the attainment of bliss is stated as the purpose of transcending the Gunas. And by 'being freed from birth, death, old age, and sorrow', the cessation of evils is declared.",
            "be": "।।১৪.২০।। 'আপনার ভাব কীভাবে প্রাপ্ত হয়?' — এর উত্তরে বলছেন: 'গুণান্' ইত্যাদি। মহদাদি তেইশটি বিকারের রূপে পরিণত, স্থূল দেহের উৎপত্তির কারণস্বরূপ এই গুণগুলিকে জীবিত থাকতেই নির্বিকল্পক সমাধির অভ্যাসের দ্বারা অতিক্রম (বাধ্য) করে অমৃত অর্থাৎ মোক্ষ লাভ করেন। এর দ্বারা আনন্দের প্রাপ্তিকে গুণাতীততার প্রয়োজন বলা হয়েছে। এবং 'জন্মমৃত্যুজরাদুঃখৈঃ বিমুক্তঃ সন্' এর দ্বারা অনর্থের নিবৃত্তি বলা হয়েছে।",
            "ka": "।।೧೪.೨೦।। 'ನಿನ್ನ ಭಾವವನ್ನು ಹೇಗೆ ಪಡೆಯುತ್ತಾನೆ?' - ಎಂಬುದಕ್ಕೆ ಹೇಳುತ್ತಾರೆ: 'ಗುಣಾನ್' ಇತ್ಯಾದಿ. ಮಹದಾದಿ ಇಪ್ಪತ್ತಮೂರು ವಿಕಾರಗಳ ರೂಪದಲ್ಲಿ ಪರಿಣಮಿಸಿದ, ಸ್ಥೂಲ ಶರೀರದ ಉತ್ಪತ್ತಿಗೆ ಕಾರಣವಾದ ಈ ಗುಣಗಳನ್ನು ಜೀವಂತವಾಗಿದ್ದಾಗಲೇ ನಿರ್ವಿಕಲ್ಪಕ ಸಮಾಧಿಯ ಅಭ್ಯಾಸದಿಂದ ಮೀರಿ (ಬಾಧಿಸಿ) ಅಮೃತ ಅಂದರೆ ಮೋಕ್ಷವನ್ನು ಪಡೆಯುತ್ತಾನೆ. ಇದರಿಂದ ಆನಂದದ ಪ್ರಾಪ್ತಿಯನ್ನು ಗುಣಾತೀತತೆಯ ಪ್ರಯೋಜನವೆಂದು ಹೇಳಲಾಗಿದೆ. ಮತ್ತು 'ಜನ್ಮಮೃತ್ಯುಜರಾದುಃಖೈರ್ವಿಮುಕ್ತಃ ಸನ್' ಎಂಬುದರಿಂದ ಅನರ್ಥದ ನಿವೃತ್ತಿಯನ್ನು ಹೇಳಲಾಗಿದೆ.",
            "sa": "।।14.20।।कथं त्वद्भावं गच्छतीति तत्राह -- गुणानिति। एतान्गुणान् महदादित्रयोविंशतिविकारात्मना,परिणतान् देहसमुद्भवान् स्थूलदेहस्य समुद्भवो येभ्यस्तानतीत्य जीवन्नेवातिक्रम्य निर्विकल्पकसमाध्यभ्यासेन बाधित्वाऽमृतं मोक्षमश्नुते प्राप्नोति। एतेनानन्दावाप्तिर्गुणात्ययप्रयोजनमुक्तम्। यतो मुक्तो जन्ममृत्युजरादुःखैर्विमुक्तः सन्निति त्वनर्थनिवृत्तिरुक्ता।"
        }
    },
    "prabhu": {
        "author": "A.C. Bhaktivedanta Swami Prabhupada",
        "commentary": {
            "hi": "जब देहधारी जीव भौतिक शरीर से सम्बद्ध इन तीनों गुणों को लांघने में समर्थ होता है, तब वह जन्म, मृत्यु, जरा तथा इनके कष्टों से मुक्त हो सकता है और इसी जीवन में अमृत का भोग कर सकता है।\n\nतात्पर्य: इस श्लोक में यह व्याख्या की गई है कि मनुष्य पूर्ण कृष्णभावनाभावित होकर इस शरीर में रहते हुए भी गुणातीत स्थिति में किस प्रकार रह सकता है। संस्कृत शब्द 'देही' का अर्थ है 'देहधारी'। यद्यपि मनुष्य इस भौतिक शरीर के भीतर है, किन्तु आध्यात्मिक ज्ञान में अपनी प्रगति के द्वारा वह प्रकृति के गुणों के प्रभाव से मुक्त हो सकता है। वह इसी शरीर में रहते हुए आध्यात्मिक जीवन के सुख का उपभोग कर सकता है, क्योंकि इस शरीर को छोड़ने के पश्चात् उसका आध्यात्मिक आकाश में जाना निश्चित है। किन्तु इसी शरीर में भी वह आध्यात्मिक सुख का उपभोग कर सकता है। दूसरे शब्दों में, कृष्णभावनाभावित भक्ति ही भौतिक उलझन से मुक्ति का लक्षण है और इसकी व्याख्या अठारहवें अध्याय में की जाएगी। जब मनुष्य भौतिक प्रकृति के गुणों के प्रभाव से मुक्त हो जाता है, तब वह भक्तिमय सेवा में प्रवेश करता है।",
            "en": "When the embodied being is able to transcend these three modes associated with the material body, he can become free from birth, death, old age and their distresses and can enjoy nectar even in this life.\n\n How one can stay in the transcendental position, even in this body, in full Kṛṣṇa consciousness, is explained in this verse. The Sanskrit word dehī means “embodied.” Although one is within this material body, by his advancement in spiritual knowledge he can be free from the influence of the modes of nature. He can enjoy the happiness of spiritual life even in this body because, after leaving this body, he is certainly going to the spiritual sky. But even in this body he can enjoy spiritual happiness. In other words, devotional service in Kṛṣṇa consciousness is the sign of liberation from material entanglement, and this will be explained in the Eighteenth Chapter. When one is freed from the influence of the modes of material nature, he enters into devotional service.",
            "be": "যখন দেহধারী জীব ভৌতিক শরীরের সাথে সম্পর্কিত এই তিনটি গুণকে অতিক্রম করতে সমর্থ হন, তখন তিনি জন্ম, মৃত্যু, জরা এবং এদের কষ্ট থেকে মুক্ত হতে পারেন এবং এই জীবনেই অমৃত ভোগ করতে পারেন।\n\nতাৎপর্য: এই শ্লোকে ব্যাখ্যা করা হয়েছে যে কীভাবে মানুষ পূর্ণ কৃষ্ণভাবনামৃতের মাধ্যমে এই শরীরে থেকেও গুণাতীত স্থিতিতে অবস্থান করতে পারে। সংস্কৃত শব্দ 'দেহী' এর অর্থ 'দেহধারী'। যদিও মানুষ এই ভৌতিক শরীরের মধ্যে রয়েছে, তথাপি আধ্যাত্মিক জ্ঞানে অগ্রগতির দ্বারা সে প্রকৃতির গুণের প্রভাব থেকে মুক্ত হতে পারে। সে এই শরীরে থেকেই আধ্যাত্মিক জীবনের সুখ উপভোগ করতে পারে, কারণ এই শরীর ত্যাগের পর তার আধ্যাত্মিক আকাশে গমন নিশ্চিত। কিন্তু এই শরীরে থাকলেও সে আধ্যাত্মিক সুখ উপভোগ করতে পারে। অন্য কথায়, কৃষ্ণভাবনাময় ভক্তিসেবাই ভৌতিক জড়াজাল থেকে মুক্তির লক্ষণ, এবং এটি অষ্টাদশ অধ্যায়ে ব্যাখ্যা করা হবে। যখন কেউ ভৌতিক প্রকৃতির গুণের প্রভাব থেকে মুক্ত হয়, তখন সে ভক্তিসেবায় প্রবেশ করে।",
            "ka": "ದೇಹಧಾರಿಯಾದ ಜೀವಿಯು ಭೌತಿಕ ಶರೀರಕ್ಕೆ ಸಂಬಂಧಿಸಿದ ಈ ಮೂರು ಗುಣಗಳನ್ನು ಮೀರಲು ಸಮರ್ಥನಾದಾಗ, ಅವನು ಜನ್ಮ, ಮೃತ್ಯು, ಮುಪ್ಪು ಮತ್ತು ಅವುಗಳ ಕ್ಲೇಶಗಳಿಂದ ಮುಕ್ತನಾಗಬಹುದು ಮತ್ತು ಈ ಜನ್ಮದಲ್ಲಿಯೇ ಅಮೃತವನ್ನು ಅನುಭವಿಸಬಹುದು.\n\nತಾತ್ಪರ್ಯ: ಸಂಪೂರ್ಣ ಕೃಷ್ಣಪ್ರಜ್ಞೆಯಲ್ಲಿ ಈ ಶರೀರದಲ್ಲಿಯೇ ಇದ್ದುಕೊಂಡು ಗುಣಾತೀತ ಸ್ಥಿತಿಯಲ್ಲಿ ಹೇಗೆ ಇರಬಹುದು ಎಂಬುದನ್ನು ಈ ಶ್ಲೋಕದಲ್ಲಿ ವಿವರಿಸಲಾಗಿದೆ. ಸಂಸ್ಕೃತ ಪದ 'ದೇಹೀ' ಎಂದರೆ 'ದೇಹಧಾರಿ'. ಮನುಷ್ಯನು ಈ ಭೌತಿಕ ಶರೀರದ ಒಳಗಿದ್ದರೂ, ಆಧ್ಯಾತ್ಮಿಕ ಜ್ಞಾನದಲ್ಲಿ ತನ್ನ ಪ್ರಗತಿಯಿಂದ ಅವನು ಪ್ರಕೃತಿಯ ಗುಣಗಳ ಪ್ರಭಾವದಿಂದ ಮುಕ್ತನಾಗಬಹುದು. ಅವನು ಈ ಶರೀರದಲ್ಲಿಯೇ ಆಧ್ಯಾತ್ಮಿಕ ಜೀವನದ ಸುಖವನ್ನು ಅನುಭವಿಸಬಹುದು, ಏಕೆಂದರೆ ಈ ಶರೀರವನ್ನು ತೊರೆದ ನಂತರ ಅವನು ಆಧ್ಯಾತ್ಮಿಕ ಆಕಾಶಕ್ಕೆ ಹೋಗುವುದು ನಿಶ್ಚಿತವಾಗಿರುವುದರಿಂದ, ಅವನು ಈ ಶರೀರದಲ್ಲಿಯೇ ಆಧ್ಯಾತ್ಮಿಕ ಸುಖವನ್ನು ಅನುಭವಿಸಬಹುದು. ಆದರೆ ಈ ಶರೀರದಲ್ಲಿಯೂ ಅವನು ಆಧ್ಯಾತ್ಮಿಕ ಸುಖವನ್ನು ಅನುಭವಿಸಬಹುದು. ಇನ್ನೊಂದು ಮಾತುಗಳಲ್ಲಿ ಹೇಳುವುದಾದರೆ, ಕೃಷ್ಣಪ್ರಜ್ಞೆಯಲ್ಲಿನ ಭಕ್ತಿ ಸೇವೆಯು ಭೌತಿಕ ಬಂಧನದಿಂದ ಮುಕ್ತಿಯ ಲಕ್ಷಣವಾಗಿದೆ, ಮತ್ತು ಇದನ್ನು ಹದಿನೆಂಟನೇ ಅಧ್ಯಾಯದಲ್ಲಿ ವಿವರಿಸಲಾಗುವುದು. ಒಬ್ಬನು ಭೌತಿಕ ಪ್ರಕೃತಿಯ ಗುಣಗಳ ಪ್ರಭಾವದಿಂದ ಮುಕ್ತನಾದಾಗ, ಅವನು ಭಕ್ತಿ ಸೇವೆಯಲ್ಲಿ ಪ್ರವೇಶಿಸುತ್ತಾನೆ."
        }
    }
}
